[{"symbol":"NMDC","strikePrice":8000,"optionType":"PE","expiry":"2016-07-28","ts":"NMDC26JUL80PE"},{"symbol":"NMDC","strikePrice":8200,"optionType":"CE","expiry":"2016-07-28","ts":"NMDC26JUL82CE"},{"symbol":"NMDC","strikePrice":8600,"optionType":"CE","expiry":"2016-07-28","ts":"NMDC26JUL86CE"},{"symbol":"NMDC","strikePrice":9200,"optionType":"CE","expiry":"2016-07-28","ts":"NMDC26JUL92CE"},{"symbol":"NMDC","strikePrice":9400,"optionType":"CE","expiry":"2016-07-28","ts":"NMDC26JUL94CE"},{"symbol":"NMDC","strikePrice":11600,"optionType":"CE","expiry":"2016-07-28","ts":"NMDC26JUL116CE"},{"symbol":"NMDC","strikePrice":12400,"optionType":"PE","expiry":"2016-07-28","ts":"NMDC26JUL124PE"},{"symbol":"NMDC","strikePrice":5600,"optionType":"CE","expiry":"2016-07-28","ts":"NMDC26JUL56CE"},{"symbol":"NMDC","strikePrice":5600,"optionType":"PE","expiry":"2016-07-28","ts":"NMDC26JUL56PE"},{"symbol":"NMDC","strikePrice":6000,"optionType":"CE","expiry":"2016-07-28","ts":"NMDC26JUL60CE"},{"symbol":"NMDC","strikePrice":7800,"optionType":"CE","expiry":"2016-07-28","ts":"NMDC26JUL78CE"},{"symbol":"NMDC","strikePrice":8000,"optionType":"CE","expiry":"2016-07-28","ts":"NMDC26JUL80CE"},{"symbol":"NMDC","strikePrice":8400,"optionType":"PE","expiry":"2016-07-28","ts":"NMDC26JUL84PE"},{"symbol":"NMDC","strikePrice":8600,"optionType":"PE","expiry":"2016-07-28","ts":"NMDC26JUL86PE"},{"symbol":"NMDC","strikePrice":9600,"optionType":"CE","expiry":"2016-07-28","ts":"NMDC26JUL96CE"},{"symbol":"NMDC","strikePrice":5800,"optionType":"PE","expiry":"2016-07-28","ts":"NMDC26JUL58PE"},{"symbol":"NMDC","strikePrice":7900,"optionType":"CE","expiry":"2016-07-28","ts":"NMDC26JUL79CE"},{"symbol":"NMDC","strikePrice":8100,"optionType":"PE","expiry":"2016-07-28","ts":"NMDC26JUL81PE"},{"symbol":"NMDC","strikePrice":8300,"optionType":"CE","expiry":"2016-07-28","ts":"NMDC26JUL83CE"},{"symbol":"NMDC","strikePrice":9500,"optionType":"CE","expiry":"2016-07-28","ts":"NMDC26JUL95CE"},{"symbol":"NMDC","strikePrice":9700,"optionType":"PE","expiry":"2016-07-28","ts":"NMDC26JUL97PE"},{"symbol":"NMDC","strikePrice":10900,"optionType":"PE","expiry":"2016-07-28","ts":"NMDC26JUL109PE"},{"symbol":"NMDC","strikePrice":11100,"optionType":"PE","expiry":"2016-07-28","ts":"NMDC26JUL111PE"},{"symbol":"NMDC","strikePrice":5600,"optionType":"CE","expiry":"2016-08-25","ts":"NMDC26AUG56CE"},{"symbol":"NMDC","strikePrice":6400,"optionType":"PE","expiry":"2016-08-25","ts":"NMDC26AUG64PE"},{"symbol":"NMDC","strikePrice":8800,"optionType":"CE","expiry":"2016-08-25","ts":"NMDC26AUG88CE"},{"symbol":"NMDC","strikePrice":8800,"optionType":"PE","expiry":"2016-08-25","ts":"NMDC26AUG88PE"},{"symbol":"NMDC","strikePrice":9400,"optionType":"CE","expiry":"2016-08-25","ts":"NMDC26AUG94CE"},{"symbol":"NMDC","strikePrice":7400,"optionType":"CE","expiry":"2016-07-28","ts":"NMDC26JUL74CE"},{"symbol":"NMDC","strikePrice":8800,"optionType":"CE","expiry":"2016-07-28","ts":"NMDC26JUL88CE"},{"symbol":"NMDC","strikePrice":9000,"optionType":"CE","expiry":"2016-07-28","ts":"NMDC26JUL90CE"},{"symbol":"NMDC","strikePrice":7700,"optionType":"PE","expiry":"2016-07-28","ts":"NMDC26JUL77PE"},{"symbol":"NMDC","strikePrice":6400,"optionType":"CE","expiry":"2016-07-28","ts":"NMDC26JUL64CE"},{"symbol":"NMDC","strikePrice":6800,"optionType":"PE","expiry":"2016-07-28","ts":"NMDC26JUL68PE"},{"symbol":"NMDC","strikePrice":7200,"optionType":"CE","expiry":"2016-07-28","ts":"NMDC26JUL72CE"},{"symbol":"NMDC","strikePrice":9000,"optionType":"PE","expiry":"2016-07-28","ts":"NMDC26JUL90PE"},{"symbol":"NMDC","strikePrice":9400,"optionType":"PE","expiry":"2016-07-28","ts":"NMDC26JUL94PE"},{"symbol":"NMDC","strikePrice":9800,"optionType":"CE","expiry":"2016-07-28","ts":"NMDC26JUL98CE"},{"symbol":"NMDC","strikePrice":11000,"optionType":"PE","expiry":"2016-07-28","ts":"NMDC26JUL110PE"},{"symbol":"NMDC","strikePrice":7600,"optionType":"CE","expiry":"2016-07-28","ts":"NMDC26JUL76CE"},{"symbol":"NMDC","strikePrice":8200,"optionType":"PE","expiry":"2016-07-28","ts":"NMDC26JUL82PE"},{"symbol":"NMDC","strikePrice":10400,"optionType":"PE","expiry":"2016-07-28","ts":"NMDC26JUL104PE"},{"symbol":"NMDC","strikePrice":11400,"optionType":"CE","expiry":"2016-07-28","ts":"NMDC26JUL114CE"},{"symbol":"NMDC","strikePrice":11400,"optionType":"PE","expiry":"2016-07-28","ts":"NMDC26JUL114PE"},{"symbol":"NMDC","strikePrice":12000,"optionType":"CE","expiry":"2016-07-28","ts":"NMDC26JUL120CE"},{"symbol":"NMDC","strikePrice":12400,"optionType":"CE","expiry":"2016-07-28","ts":"NMDC26JUL124CE"},{"symbol":"NMDC","strikePrice":10200,"optionType":"CE","expiry":"2016-07-28","ts":"NMDC26JUL102CE"},{"symbol":"NMDC","strikePrice":10400,"optionType":"CE","expiry":"2016-07-28","ts":"NMDC26JUL104CE"},{"symbol":"NMDC","strikePrice":10600,"optionType":"CE","expiry":"2016-07-28","ts":"NMDC26JUL106CE"},{"symbol":"NMDC","strikePrice":10800,"optionType":"CE","expiry":"2016-07-28","ts":"NMDC26JUL108CE"},{"symbol":"NMDC","strikePrice":11200,"optionType":"PE","expiry":"2016-07-28","ts":"NMDC26JUL112PE"},{"symbol":"NMDC","strikePrice":8500,"optionType":"PE","expiry":"2016-07-28","ts":"NMDC26JUL85PE"},{"symbol":"NMDC","strikePrice":8700,"optionType":"PE","expiry":"2016-07-28","ts":"NMDC26JUL87PE"},{"symbol":"NMDC","strikePrice":9700,"optionType":"CE","expiry":"2016-07-28","ts":"NMDC26JUL97CE"},{"symbol":"NMDC","strikePrice":10100,"optionType":"CE","expiry":"2016-07-28","ts":"NMDC26JUL101CE"},{"symbol":"NMDC","strikePrice":6800,"optionType":"PE","expiry":"2016-08-25","ts":"NMDC26AUG68PE"},{"symbol":"NMDC","strikePrice":7400,"optionType":"PE","expiry":"2016-08-25","ts":"NMDC26AUG74PE"},{"symbol":"NMDC","strikePrice":7700,"optionType":"CE","expiry":"2016-07-28","ts":"NMDC26JUL77CE"},{"symbol":"NMDC","strikePrice":8100,"optionType":"CE","expiry":"2016-07-28","ts":"NMDC26JUL81CE"},{"symbol":"NMDC","strikePrice":8300,"optionType":"PE","expiry":"2016-07-28","ts":"NMDC26JUL83PE"},{"symbol":"NMDC","strikePrice":8700,"optionType":"CE","expiry":"2016-07-28","ts":"NMDC26JUL87CE"},{"symbol":"NMDC","strikePrice":8900,"optionType":"CE","expiry":"2016-07-28","ts":"NMDC26JUL89CE"},{"symbol":"NMDC","strikePrice":10300,"optionType":"PE","expiry":"2016-07-28","ts":"NMDC26JUL103PE"},{"symbol":"NMDC","strikePrice":11100,"optionType":"CE","expiry":"2016-07-28","ts":"NMDC26JUL111CE"},{"symbol":"NMDC","strikePrice":5600,"optionType":"PE","expiry":"2016-08-25","ts":"NMDC26AUG56PE"},{"symbol":"NMDC","strikePrice":6400,"optionType":"CE","expiry":"2016-08-25","ts":"NMDC26AUG64CE"},{"symbol":"NMDC","strikePrice":7000,"optionType":"PE","expiry":"2016-08-25","ts":"NMDC26AUG70PE"},{"symbol":"NMDC","strikePrice":7200,"optionType":"PE","expiry":"2016-08-25","ts":"NMDC26AUG72PE"},{"symbol":"NMDC","strikePrice":7600,"optionType":"CE","expiry":"2016-08-25","ts":"NMDC26AUG76CE"},{"symbol":"NMDC","strikePrice":8000,"optionType":"CE","expiry":"2016-08-25","ts":"NMDC26AUG80CE"},{"symbol":"NMDC","strikePrice":8400,"optionType":"PE","expiry":"2016-08-25","ts":"NMDC26AUG84PE"},{"symbol":"NMDC","strikePrice":9000,"optionType":"PE","expiry":"2016-08-25","ts":"NMDC26AUG90PE"},{"symbol":"NMDC","strikePrice":9400,"optionType":"PE","expiry":"2016-08-25","ts":"NMDC26AUG94PE"},{"symbol":"NMDC","strikePrice":9800,"optionType":"CE","expiry":"2016-08-25","ts":"NMDC26AUG98CE"},{"symbol":"NMDC","strikePrice":11200,"optionType":"CE","expiry":"2016-08-25","ts":"NMDC26AUG112CE"},{"symbol":"NMDC","strikePrice":11600,"optionType":"CE","expiry":"2016-08-25","ts":"NMDC26AUG116CE"},{"symbol":"NMDC","strikePrice":7100,"optionType":"CE","expiry":"2016-07-28","ts":"NMDC26JUL71CE"},{"symbol":"NMDC","strikePrice":7500,"optionType":"CE","expiry":"2016-07-28","ts":"NMDC26JUL75CE"},{"symbol":"NMDC","strikePrice":4600,"optionType":"PE","expiry":"2016-07-28","ts":"NMDC26JUL46PE"},{"symbol":"NMDC","strikePrice":5900,"optionType":"CE","expiry":"2016-07-28","ts":"NMDC26JUL59CE"},{"symbol":"NMDC","strikePrice":4600,"optionType":"PE","expiry":"2016-08-25","ts":"NMDC26AUG46PE"},{"symbol":"NMDC","strikePrice":5000,"optionType":"CE","expiry":"2016-08-25","ts":"NMDC26AUG50CE"},{"symbol":"NMDC","strikePrice":5800,"optionType":"PE","expiry":"2016-08-25","ts":"NMDC26AUG58PE"},{"symbol":"NMDC","strikePrice":6500,"optionType":"PE","expiry":"2016-08-25","ts":"NMDC26AUG65PE"},{"symbol":"NMDC","strikePrice":7500,"optionType":"PE","expiry":"2016-08-25","ts":"NMDC26AUG75PE"},{"symbol":"NMDC","strikePrice":8300,"optionType":"CE","expiry":"2016-08-25","ts":"NMDC26AUG83CE"},{"symbol":"NMDC","strikePrice":9300,"optionType":"CE","expiry":"2016-08-25","ts":"NMDC26AUG93CE"},{"symbol":"NMDC","strikePrice":12200,"optionType":"PE","expiry":"2016-08-25","ts":"NMDC26AUG122PE"},{"symbol":"NMDC","strikePrice":4800,"optionType":"CE","expiry":"2016-09-29","ts":"NMDC26SEP48CE"},{"symbol":"NMDC","strikePrice":4800,"optionType":"PE","expiry":"2016-09-29","ts":"NMDC26SEP48PE"},{"symbol":"NMDC","strikePrice":5200,"optionType":"PE","expiry":"2016-09-29","ts":"NMDC26SEP52PE"},{"symbol":"NMDC","strikePrice":5600,"optionType":"PE","expiry":"2016-09-29","ts":"NMDC26SEP56PE"},{"symbol":"NMDC","strikePrice":6400,"optionType":"CE","expiry":"2016-09-29","ts":"NMDC26SEP64CE"},{"symbol":"NMDC","strikePrice":7400,"optionType":"CE","expiry":"2016-09-29","ts":"NMDC26SEP74CE"},{"symbol":"NMDC","strikePrice":7600,"optionType":"PE","expiry":"2016-09-29","ts":"NMDC26SEP76PE"},{"symbol":"NMDC","strikePrice":8400,"optionType":"CE","expiry":"2016-09-29","ts":"NMDC26SEP84CE"},{"symbol":"NMDC","strikePrice":9200,"optionType":"PE","expiry":"2016-09-29","ts":"NMDC26SEP92PE"},{"symbol":"NMDC","strikePrice":9800,"optionType":"PE","expiry":"2016-09-29","ts":"NMDC26SEP98PE"},{"symbol":"NMDC","strikePrice":6900,"optionType":"PE","expiry":"2016-07-28","ts":"NMDC26JUL69PE"},{"symbol":"NMDC","strikePrice":7300,"optionType":"CE","expiry":"2016-07-28","ts":"NMDC26JUL73CE"},{"symbol":"NMDC","strikePrice":8900,"optionType":"PE","expiry":"2016-07-28","ts":"NMDC26JUL89PE"},{"symbol":"NMDC","strikePrice":9100,"optionType":"PE","expiry":"2016-07-28","ts":"NMDC26JUL91PE"},{"symbol":"NMDC","strikePrice":9300,"optionType":"CE","expiry":"2016-07-28","ts":"NMDC26JUL93CE"},{"symbol":"NMDC","strikePrice":10500,"optionType":"PE","expiry":"2016-07-28","ts":"NMDC26JUL105PE"},{"symbol":"NMDC","strikePrice":8600,"optionType":"PE","expiry":"2016-08-25","ts":"NMDC26AUG86PE"},{"symbol":"NMDC","strikePrice":10000,"optionType":"PE","expiry":"2016-08-25","ts":"NMDC26AUG100PE"},{"symbol":"NMDC","strikePrice":11000,"optionType":"PE","expiry":"2016-08-25","ts":"NMDC26AUG110PE"},{"symbol":"NMDC","strikePrice":11600,"optionType":"PE","expiry":"2016-08-25","ts":"NMDC26AUG116PE"},{"symbol":"NMDC","strikePrice":12400,"optionType":"PE","expiry":"2016-08-25","ts":"NMDC26AUG124PE"},{"symbol":"NMDC","strikePrice":7000,"optionType":"PE","expiry":"2016-07-28","ts":"NMDC26JUL70PE"},{"symbol":"NMDC","strikePrice":7200,"optionType":"PE","expiry":"2016-07-28","ts":"NMDC26JUL72PE"},{"symbol":"NMDC","strikePrice":7400,"optionType":"PE","expiry":"2016-07-28","ts":"NMDC26JUL74PE"},{"symbol":"NMDC","strikePrice":7800,"optionType":"PE","expiry":"2016-07-28","ts":"NMDC26JUL78PE"},{"symbol":"NMDC","strikePrice":8400,"optionType":"CE","expiry":"2016-07-28","ts":"NMDC26JUL84CE"},{"symbol":"NMDC","strikePrice":9200,"optionType":"PE","expiry":"2016-07-28","ts":"NMDC26JUL92PE"},{"symbol":"NMDC","strikePrice":4400,"optionType":"CE","expiry":"2016-07-28","ts":"NMDC26JUL44CE"},{"symbol":"NMDC","strikePrice":5900,"optionType":"PE","expiry":"2016-07-28","ts":"NMDC26JUL59PE"},{"symbol":"NMDC","strikePrice":5800,"optionType":"CE","expiry":"2016-07-28","ts":"NMDC26JUL58CE"},{"symbol":"NMDC","strikePrice":7300,"optionType":"PE","expiry":"2016-07-28","ts":"NMDC26JUL73PE"},{"symbol":"NMDC","strikePrice":10100,"optionType":"PE","expiry":"2016-07-28","ts":"NMDC26JUL101PE"},{"symbol":"NMDC","strikePrice":10300,"optionType":"CE","expiry":"2016-07-28","ts":"NMDC26JUL103CE"},{"symbol":"NMDC","strikePrice":10500,"optionType":"CE","expiry":"2016-07-28","ts":"NMDC26JUL105CE"},{"symbol":"NMDC","strikePrice":10700,"optionType":"PE","expiry":"2016-07-28","ts":"NMDC26JUL107PE"},{"symbol":"NMDC","strikePrice":12600,"optionType":"CE","expiry":"2016-07-28","ts":"NMDC26JUL126CE"},{"symbol":"NMDC","strikePrice":7000,"optionType":"CE","expiry":"2016-08-25","ts":"NMDC26AUG70CE"},{"symbol":"NMDC","strikePrice":8200,"optionType":"CE","expiry":"2016-08-25","ts":"NMDC26AUG82CE"},{"symbol":"NMDC","strikePrice":10000,"optionType":"CE","expiry":"2016-08-25","ts":"NMDC26AUG100CE"},{"symbol":"NMDC","strikePrice":10800,"optionType":"PE","expiry":"2016-08-25","ts":"NMDC26AUG108PE"},{"symbol":"NMDC","strikePrice":11200,"optionType":"PE","expiry":"2016-08-25","ts":"NMDC26AUG112PE"},{"symbol":"NMDC","strikePrice":11400,"optionType":"PE","expiry":"2016-08-25","ts":"NMDC26AUG114PE"},{"symbol":"NMDC","strikePrice":6900,"optionType":"CE","expiry":"2016-07-28","ts":"NMDC26JUL69CE"},{"symbol":"NMDC","strikePrice":7100,"optionType":"PE","expiry":"2016-07-28","ts":"NMDC26JUL71PE"},{"symbol":"NMDC","strikePrice":7500,"optionType":"PE","expiry":"2016-07-28","ts":"NMDC26JUL75PE"},{"symbol":"NMDC","strikePrice":9100,"optionType":"CE","expiry":"2016-07-28","ts":"NMDC26JUL91CE"},{"symbol":"NMDC","strikePrice":9900,"optionType":"CE","expiry":"2016-07-28","ts":"NMDC26JUL99CE"},{"symbol":"NMDC","strikePrice":10700,"optionType":"CE","expiry":"2016-07-28","ts":"NMDC26JUL107CE"},{"symbol":"NMDC","strikePrice":12200,"optionType":"CE","expiry":"2016-07-28","ts":"NMDC26JUL122CE"},{"symbol":"NMDC","strikePrice":12200,"optionType":"PE","expiry":"2016-07-28","ts":"NMDC26JUL122PE"},{"symbol":"NMDC","strikePrice":6000,"optionType":"CE","expiry":"2016-08-25","ts":"NMDC26AUG60CE"},{"symbol":"NMDC","strikePrice":6000,"optionType":"PE","expiry":"2016-08-25","ts":"NMDC26AUG60PE"},{"symbol":"NMDC","strikePrice":7800,"optionType":"PE","expiry":"2016-08-25","ts":"NMDC26AUG78PE"},{"symbol":"NMDC","strikePrice":8600,"optionType":"CE","expiry":"2016-08-25","ts":"NMDC26AUG86CE"},{"symbol":"NMDC","strikePrice":9200,"optionType":"CE","expiry":"2016-08-25","ts":"NMDC26AUG92CE"},{"symbol":"NMDC","strikePrice":9200,"optionType":"PE","expiry":"2016-08-25","ts":"NMDC26AUG92PE"},{"symbol":"NMDC","strikePrice":10200,"optionType":"CE","expiry":"2016-08-25","ts":"NMDC26AUG102CE"},{"symbol":"NMDC","strikePrice":10400,"optionType":"CE","expiry":"2016-08-25","ts":"NMDC26AUG104CE"},{"symbol":"NMDC","strikePrice":10400,"optionType":"PE","expiry":"2016-08-25","ts":"NMDC26AUG104PE"},{"symbol":"NMDC","strikePrice":6500,"optionType":"CE","expiry":"2016-08-25","ts":"NMDC26AUG65CE"},{"symbol":"NMDC","strikePrice":6700,"optionType":"CE","expiry":"2016-08-25","ts":"NMDC26AUG67CE"},{"symbol":"NMDC","strikePrice":8100,"optionType":"CE","expiry":"2016-08-25","ts":"NMDC26AUG81CE"},{"symbol":"NMDC","strikePrice":9100,"optionType":"PE","expiry":"2016-08-25","ts":"NMDC26AUG91PE"},{"symbol":"NMDC","strikePrice":9700,"optionType":"CE","expiry":"2016-08-25","ts":"NMDC26AUG97CE"},{"symbol":"NMDC","strikePrice":10500,"optionType":"CE","expiry":"2016-08-25","ts":"NMDC26AUG105CE"},{"symbol":"NMDC","strikePrice":10500,"optionType":"PE","expiry":"2016-08-25","ts":"NMDC26AUG105PE"},{"symbol":"NMDC","strikePrice":12600,"optionType":"CE","expiry":"2016-08-25","ts":"NMDC26AUG126CE"},{"symbol":"NMDC","strikePrice":6000,"optionType":"CE","expiry":"2016-09-29","ts":"NMDC26SEP60CE"},{"symbol":"NMDC","strikePrice":6000,"optionType":"PE","expiry":"2016-09-29","ts":"NMDC26SEP60PE"},{"symbol":"NMDC","strikePrice":6200,"optionType":"CE","expiry":"2016-09-29","ts":"NMDC26SEP62CE"},{"symbol":"NMDC","strikePrice":8200,"optionType":"CE","expiry":"2016-09-29","ts":"NMDC26SEP82CE"},{"symbol":"NMDC","strikePrice":8400,"optionType":"PE","expiry":"2016-09-29","ts":"NMDC26SEP84PE"},{"symbol":"NMDC","strikePrice":8600,"optionType":"CE","expiry":"2016-09-29","ts":"NMDC26SEP86CE"},{"symbol":"NMDC","strikePrice":8800,"optionType":"PE","expiry":"2016-09-29","ts":"NMDC26SEP88PE"},{"symbol":"NMDC","strikePrice":9200,"optionType":"CE","expiry":"2016-09-29","ts":"NMDC26SEP92CE"},{"symbol":"NMDC","strikePrice":9400,"optionType":"PE","expiry":"2016-09-29","ts":"NMDC26SEP94PE"},{"symbol":"NMDC","strikePrice":10400,"optionType":"CE","expiry":"2016-09-29","ts":"NMDC26SEP104CE"},{"symbol":"NMDC","strikePrice":10800,"optionType":"CE","expiry":"2016-09-29","ts":"NMDC26SEP108CE"},{"symbol":"NMDC","strikePrice":11200,"optionType":"CE","expiry":"2016-09-29","ts":"NMDC26SEP112CE"},{"symbol":"NMDC","strikePrice":11200,"optionType":"PE","expiry":"2016-09-29","ts":"NMDC26SEP112PE"},{"symbol":"NMDC","strikePrice":7800,"optionType":"CE","expiry":"2016-08-25","ts":"NMDC26AUG78CE"},{"symbol":"NMDC","strikePrice":9000,"optionType":"CE","expiry":"2016-08-25","ts":"NMDC26AUG90CE"},{"symbol":"NMDC","strikePrice":9600,"optionType":"CE","expiry":"2016-08-25","ts":"NMDC26AUG96CE"},{"symbol":"NMDC","strikePrice":9600,"optionType":"PE","expiry":"2016-08-25","ts":"NMDC26AUG96PE"},{"symbol":"NMDC","strikePrice":10600,"optionType":"PE","expiry":"2016-08-25","ts":"NMDC26AUG106PE"},{"symbol":"NMDC","strikePrice":11000,"optionType":"CE","expiry":"2016-08-25","ts":"NMDC26AUG110CE"},{"symbol":"NMDC","strikePrice":12000,"optionType":"PE","expiry":"2016-08-25","ts":"NMDC26AUG120PE"},{"symbol":"NMDC","strikePrice":12400,"optionType":"CE","expiry":"2016-08-25","ts":"NMDC26AUG124CE"},{"symbol":"NMDC","strikePrice":5000,"optionType":"PE","expiry":"2016-08-25","ts":"NMDC26AUG50PE"},{"symbol":"NMDC","strikePrice":5900,"optionType":"PE","expiry":"2016-08-25","ts":"NMDC26AUG59PE"},{"symbol":"NMDC","strikePrice":6700,"optionType":"PE","expiry":"2016-08-25","ts":"NMDC26AUG67PE"},{"symbol":"NMDC","strikePrice":7300,"optionType":"PE","expiry":"2016-08-25","ts":"NMDC26AUG73PE"},{"symbol":"NMDC","strikePrice":7900,"optionType":"CE","expiry":"2016-08-25","ts":"NMDC26AUG79CE"},{"symbol":"NMDC","strikePrice":8100,"optionType":"PE","expiry":"2016-08-25","ts":"NMDC26AUG81PE"},{"symbol":"NMDC","strikePrice":8500,"optionType":"PE","expiry":"2016-08-25","ts":"NMDC26AUG85PE"},{"symbol":"NMDC","strikePrice":8700,"optionType":"CE","expiry":"2016-08-25","ts":"NMDC26AUG87CE"},{"symbol":"NMDC","strikePrice":8700,"optionType":"PE","expiry":"2016-08-25","ts":"NMDC26AUG87PE"},{"symbol":"NMDC","strikePrice":9900,"optionType":"PE","expiry":"2016-08-25","ts":"NMDC26AUG99PE"},{"symbol":"NMDC","strikePrice":10300,"optionType":"PE","expiry":"2016-08-25","ts":"NMDC26AUG103PE"},{"symbol":"NMDC","strikePrice":7600,"optionType":"CE","expiry":"2016-09-29","ts":"NMDC26SEP76CE"},{"symbol":"NMDC","strikePrice":8000,"optionType":"PE","expiry":"2016-09-29","ts":"NMDC26SEP80PE"},{"symbol":"NMDC","strikePrice":9600,"optionType":"CE","expiry":"2016-09-29","ts":"NMDC26SEP96CE"},{"symbol":"NMDC","strikePrice":10000,"optionType":"PE","expiry":"2016-09-29","ts":"NMDC26SEP100PE"},{"symbol":"NMDC","strikePrice":10200,"optionType":"PE","expiry":"2016-09-29","ts":"NMDC26SEP102PE"},{"symbol":"NMDC","strikePrice":8500,"optionType":"CE","expiry":"2016-07-28","ts":"NMDC26JUL85CE"},{"symbol":"NMDC","strikePrice":9300,"optionType":"PE","expiry":"2016-07-28","ts":"NMDC26JUL93PE"},{"symbol":"NMDC","strikePrice":9500,"optionType":"PE","expiry":"2016-07-28","ts":"NMDC26JUL95PE"},{"symbol":"NMDC","strikePrice":10900,"optionType":"CE","expiry":"2016-07-28","ts":"NMDC26JUL109CE"},{"symbol":"NMDC","strikePrice":7200,"optionType":"CE","expiry":"2016-08-25","ts":"NMDC26AUG72CE"},{"symbol":"NMDC","strikePrice":8000,"optionType":"PE","expiry":"2016-08-25","ts":"NMDC26AUG80PE"},{"symbol":"NMDC","strikePrice":8200,"optionType":"PE","expiry":"2016-08-25","ts":"NMDC26AUG82PE"},{"symbol":"NMDC","strikePrice":8400,"optionType":"CE","expiry":"2016-08-25","ts":"NMDC26AUG84CE"},{"symbol":"NMDC","strikePrice":10600,"optionType":"CE","expiry":"2016-08-25","ts":"NMDC26AUG106CE"},{"symbol":"NMDC","strikePrice":10800,"optionType":"CE","expiry":"2016-08-25","ts":"NMDC26AUG108CE"},{"symbol":"NMDC","strikePrice":11400,"optionType":"CE","expiry":"2016-08-25","ts":"NMDC26AUG114CE"},{"symbol":"NMDC","strikePrice":6000,"optionType":"PE","expiry":"2016-07-28","ts":"NMDC26JUL60PE"},{"symbol":"NMDC","strikePrice":9800,"optionType":"PE","expiry":"2016-07-28","ts":"NMDC26JUL98PE"},{"symbol":"NMDC","strikePrice":10000,"optionType":"CE","expiry":"2016-07-28","ts":"NMDC26JUL100CE"},{"symbol":"NMDC","strikePrice":11200,"optionType":"CE","expiry":"2016-07-28","ts":"NMDC26JUL112CE"},{"symbol":"NMDC","strikePrice":12000,"optionType":"PE","expiry":"2016-07-28","ts":"NMDC26JUL120PE"},{"symbol":"NMDC","strikePrice":10800,"optionType":"PE","expiry":"2016-07-28","ts":"NMDC26JUL108PE"},{"symbol":"NMDC","strikePrice":11000,"optionType":"CE","expiry":"2016-07-28","ts":"NMDC26JUL110CE"},{"symbol":"NMDC","strikePrice":11600,"optionType":"PE","expiry":"2016-07-28","ts":"NMDC26JUL116PE"},{"symbol":"NMDC","strikePrice":7900,"optionType":"PE","expiry":"2016-07-28","ts":"NMDC26JUL79PE"},{"symbol":"NMDC","strikePrice":9900,"optionType":"PE","expiry":"2016-07-28","ts":"NMDC26JUL99PE"},{"symbol":"NMDC","strikePrice":12600,"optionType":"PE","expiry":"2016-07-28","ts":"NMDC26JUL126PE"},{"symbol":"NMDC","strikePrice":6800,"optionType":"CE","expiry":"2016-08-25","ts":"NMDC26AUG68CE"},{"symbol":"NMDC","strikePrice":7400,"optionType":"CE","expiry":"2016-08-25","ts":"NMDC26AUG74CE"},{"symbol":"NMDC","strikePrice":7600,"optionType":"PE","expiry":"2016-08-25","ts":"NMDC26AUG76PE"},{"symbol":"NMDC","strikePrice":9800,"optionType":"PE","expiry":"2016-08-25","ts":"NMDC26AUG98PE"},{"symbol":"NMDC","strikePrice":10200,"optionType":"PE","expiry":"2016-08-25","ts":"NMDC26AUG102PE"},{"symbol":"NMDC","strikePrice":12000,"optionType":"CE","expiry":"2016-08-25","ts":"NMDC26AUG120CE"},{"symbol":"NMDC","strikePrice":4400,"optionType":"PE","expiry":"2016-07-28","ts":"NMDC26JUL44PE"},{"symbol":"NMDC","strikePrice":4600,"optionType":"CE","expiry":"2016-07-28","ts":"NMDC26JUL46CE"},{"symbol":"NMDC","strikePrice":4400,"optionType":"PE","expiry":"2016-08-25","ts":"NMDC26AUG44PE"},{"symbol":"NMDC","strikePrice":5400,"optionType":"CE","expiry":"2016-08-25","ts":"NMDC26AUG54CE"},{"symbol":"NMDC","strikePrice":6400,"optionType":"PE","expiry":"2016-07-28","ts":"NMDC26JUL64PE"},{"symbol":"NMDC","strikePrice":6800,"optionType":"CE","expiry":"2016-07-28","ts":"NMDC26JUL68CE"},{"symbol":"NMDC","strikePrice":7000,"optionType":"CE","expiry":"2016-07-28","ts":"NMDC26JUL70CE"},{"symbol":"NMDC","strikePrice":7600,"optionType":"PE","expiry":"2016-07-28","ts":"NMDC26JUL76PE"},{"symbol":"NMDC","strikePrice":8800,"optionType":"PE","expiry":"2016-07-28","ts":"NMDC26JUL88PE"},{"symbol":"NMDC","strikePrice":9600,"optionType":"PE","expiry":"2016-07-28","ts":"NMDC26JUL96PE"},{"symbol":"NMDC","strikePrice":10000,"optionType":"PE","expiry":"2016-07-28","ts":"NMDC26JUL100PE"},{"symbol":"NMDC","strikePrice":10200,"optionType":"PE","expiry":"2016-07-28","ts":"NMDC26JUL102PE"},{"symbol":"NMDC","strikePrice":10600,"optionType":"PE","expiry":"2016-07-28","ts":"NMDC26JUL106PE"},{"symbol":"NMDC","strikePrice":6300,"optionType":"PE","expiry":"2016-08-25","ts":"NMDC26AUG63PE"},{"symbol":"NMDC","strikePrice":6100,"optionType":"CE","expiry":"2016-08-25","ts":"NMDC26AUG61CE"},{"symbol":"NMDC","strikePrice":7100,"optionType":"CE","expiry":"2016-08-25","ts":"NMDC26AUG71CE"},{"symbol":"NMDC","strikePrice":7300,"optionType":"CE","expiry":"2016-08-25","ts":"NMDC26AUG73CE"},{"symbol":"NMDC","strikePrice":9300,"optionType":"PE","expiry":"2016-08-25","ts":"NMDC26AUG93PE"},{"symbol":"NMDC","strikePrice":9500,"optionType":"PE","expiry":"2016-08-25","ts":"NMDC26AUG95PE"},{"symbol":"NMDC","strikePrice":10700,"optionType":"PE","expiry":"2016-08-25","ts":"NMDC26AUG107PE"},{"symbol":"NMDC","strikePrice":11100,"optionType":"PE","expiry":"2016-08-25","ts":"NMDC26AUG111PE"},{"symbol":"NMDC","strikePrice":5200,"optionType":"CE","expiry":"2016-09-29","ts":"NMDC26SEP52CE"},{"symbol":"NMDC","strikePrice":7200,"optionType":"CE","expiry":"2016-09-29","ts":"NMDC26SEP72CE"},{"symbol":"NMDC","strikePrice":7400,"optionType":"PE","expiry":"2016-09-29","ts":"NMDC26SEP74PE"},{"symbol":"NMDC","strikePrice":7800,"optionType":"PE","expiry":"2016-09-29","ts":"NMDC26SEP78PE"},{"symbol":"NMDC","strikePrice":9000,"optionType":"PE","expiry":"2016-09-29","ts":"NMDC26SEP90PE"},{"symbol":"NMDC","strikePrice":10400,"optionType":"PE","expiry":"2016-09-29","ts":"NMDC26SEP104PE"},{"symbol":"NMDC","strikePrice":10800,"optionType":"PE","expiry":"2016-09-29","ts":"NMDC26SEP108PE"},{"symbol":"NMDC","strikePrice":12000,"optionType":"PE","expiry":"2016-09-29","ts":"NMDC26SEP120PE"},{"symbol":"NMDC","strikePrice":6900,"optionType":"PE","expiry":"2016-08-25","ts":"NMDC26AUG69PE"},{"symbol":"NMDC","strikePrice":7700,"optionType":"CE","expiry":"2016-08-25","ts":"NMDC26AUG77CE"},{"symbol":"NMDC","strikePrice":9100,"optionType":"CE","expiry":"2016-08-25","ts":"NMDC26AUG91CE"},{"symbol":"NMDC","strikePrice":9700,"optionType":"PE","expiry":"2016-08-25","ts":"NMDC26AUG97PE"},{"symbol":"NMDC","strikePrice":10300,"optionType":"CE","expiry":"2016-08-25","ts":"NMDC26AUG103CE"},{"symbol":"NMDC","strikePrice":11100,"optionType":"CE","expiry":"2016-08-25","ts":"NMDC26AUG111CE"},{"symbol":"NMDC","strikePrice":12200,"optionType":"CE","expiry":"2016-08-25","ts":"NMDC26AUG122CE"},{"symbol":"NMDC","strikePrice":6200,"optionType":"PE","expiry":"2016-09-29","ts":"NMDC26SEP62PE"},{"symbol":"NMDC","strikePrice":11600,"optionType":"CE","expiry":"2016-09-29","ts":"NMDC26SEP116CE"},{"symbol":"NMDC","strikePrice":11600,"optionType":"PE","expiry":"2016-09-29","ts":"NMDC26SEP116PE"},{"symbol":"NMDC","strikePrice":8500,"optionType":"CE","expiry":"2016-08-25","ts":"NMDC26AUG85CE"},{"symbol":"NMDC","strikePrice":10100,"optionType":"CE","expiry":"2016-08-25","ts":"NMDC26AUG101CE"},{"symbol":"NMDC","strikePrice":7000,"optionType":"CE","expiry":"2016-09-29","ts":"NMDC26SEP70CE"},{"symbol":"NMDC","strikePrice":8600,"optionType":"PE","expiry":"2016-09-29","ts":"NMDC26SEP86PE"},{"symbol":"NMDC","strikePrice":8800,"optionType":"CE","expiry":"2016-09-29","ts":"NMDC26SEP88CE"},{"symbol":"NMDC","strikePrice":9000,"optionType":"CE","expiry":"2016-09-29","ts":"NMDC26SEP90CE"},{"symbol":"NMDC","strikePrice":9600,"optionType":"PE","expiry":"2016-09-29","ts":"NMDC26SEP96PE"},{"symbol":"NMDC","strikePrice":9800,"optionType":"CE","expiry":"2016-09-29","ts":"NMDC26SEP98CE"},{"symbol":"NMDC","strikePrice":12000,"optionType":"CE","expiry":"2016-09-29","ts":"NMDC26SEP120CE"},{"symbol":"NMDC","strikePrice":7700,"optionType":"PE","expiry":"2016-08-25","ts":"NMDC26AUG77PE"},{"symbol":"NMDC","strikePrice":8300,"optionType":"PE","expiry":"2016-08-25","ts":"NMDC26AUG83PE"},{"symbol":"NMDC","strikePrice":8900,"optionType":"CE","expiry":"2016-08-25","ts":"NMDC26AUG89CE"},{"symbol":"NMDC","strikePrice":8900,"optionType":"PE","expiry":"2016-08-25","ts":"NMDC26AUG89PE"},{"symbol":"NMDC","strikePrice":9500,"optionType":"CE","expiry":"2016-08-25","ts":"NMDC26AUG95CE"},{"symbol":"NMDC","strikePrice":10100,"optionType":"PE","expiry":"2016-08-25","ts":"NMDC26AUG101PE"},{"symbol":"NMDC","strikePrice":6400,"optionType":"PE","expiry":"2016-09-29","ts":"NMDC26SEP64PE"},{"symbol":"NMDC","strikePrice":7000,"optionType":"PE","expiry":"2016-09-29","ts":"NMDC26SEP70PE"},{"symbol":"NMDC","strikePrice":7200,"optionType":"PE","expiry":"2016-09-29","ts":"NMDC26SEP72PE"},{"symbol":"NMDC","strikePrice":7800,"optionType":"CE","expiry":"2016-09-29","ts":"NMDC26SEP78CE"},{"symbol":"NMDC","strikePrice":9400,"optionType":"CE","expiry":"2016-09-29","ts":"NMDC26SEP94CE"},{"symbol":"NMDC","strikePrice":10000,"optionType":"CE","expiry":"2016-09-29","ts":"NMDC26SEP100CE"},{"symbol":"NMDC","strikePrice":4400,"optionType":"CE","expiry":"2016-08-25","ts":"NMDC26AUG44CE"},{"symbol":"NMDC","strikePrice":4600,"optionType":"CE","expiry":"2016-08-25","ts":"NMDC26AUG46CE"},{"symbol":"NMDC","strikePrice":5800,"optionType":"CE","expiry":"2016-08-25","ts":"NMDC26AUG58CE"},{"symbol":"NMDC","strikePrice":6300,"optionType":"CE","expiry":"2016-08-25","ts":"NMDC26AUG63CE"},{"symbol":"NMDC","strikePrice":5400,"optionType":"PE","expiry":"2016-08-25","ts":"NMDC26AUG54PE"},{"symbol":"NMDC","strikePrice":5900,"optionType":"CE","expiry":"2016-08-25","ts":"NMDC26AUG59CE"},{"symbol":"NMDC","strikePrice":6100,"optionType":"PE","expiry":"2016-08-25","ts":"NMDC26AUG61PE"},{"symbol":"NMDC","strikePrice":6900,"optionType":"CE","expiry":"2016-08-25","ts":"NMDC26AUG69CE"},{"symbol":"NMDC","strikePrice":7100,"optionType":"PE","expiry":"2016-08-25","ts":"NMDC26AUG71PE"},{"symbol":"NMDC","strikePrice":7500,"optionType":"CE","expiry":"2016-08-25","ts":"NMDC26AUG75CE"},{"symbol":"NMDC","strikePrice":7900,"optionType":"PE","expiry":"2016-08-25","ts":"NMDC26AUG79PE"},{"symbol":"NMDC","strikePrice":9900,"optionType":"CE","expiry":"2016-08-25","ts":"NMDC26AUG99CE"},{"symbol":"NMDC","strikePrice":10700,"optionType":"CE","expiry":"2016-08-25","ts":"NMDC26AUG107CE"},{"symbol":"NMDC","strikePrice":10900,"optionType":"CE","expiry":"2016-08-25","ts":"NMDC26AUG109CE"},{"symbol":"NMDC","strikePrice":10900,"optionType":"PE","expiry":"2016-08-25","ts":"NMDC26AUG109PE"},{"symbol":"NMDC","strikePrice":12600,"optionType":"PE","expiry":"2016-08-25","ts":"NMDC26AUG126PE"},{"symbol":"NMDC","strikePrice":5600,"optionType":"CE","expiry":"2016-09-29","ts":"NMDC26SEP56CE"},{"symbol":"NMDC","strikePrice":6600,"optionType":"CE","expiry":"2016-09-29","ts":"NMDC26SEP66CE"},{"symbol":"NMDC","strikePrice":6600,"optionType":"PE","expiry":"2016-09-29","ts":"NMDC26SEP66PE"},{"symbol":"NMDC","strikePrice":6800,"optionType":"CE","expiry":"2016-09-29","ts":"NMDC26SEP68CE"},{"symbol":"NMDC","strikePrice":6800,"optionType":"PE","expiry":"2016-09-29","ts":"NMDC26SEP68PE"},{"symbol":"NMDC","strikePrice":8000,"optionType":"CE","expiry":"2016-09-29","ts":"NMDC26SEP80CE"},{"symbol":"NMDC","strikePrice":8200,"optionType":"PE","expiry":"2016-09-29","ts":"NMDC26SEP82PE"},{"symbol":"NMDC","strikePrice":10200,"optionType":"CE","expiry":"2016-09-29","ts":"NMDC26SEP102CE"},{"symbol":"NMDC","strikePrice":10600,"optionType":"CE","expiry":"2016-09-29","ts":"NMDC26SEP106CE"},{"symbol":"NMDC","strikePrice":10600,"optionType":"PE","expiry":"2016-09-29","ts":"NMDC26SEP106PE"},{"symbol":"NMDC","strikePrice":5700,"optionType":"CE","expiry":"2016-07-28","ts":"NMDC26JUL57CE"},{"symbol":"NMDC","strikePrice":4200,"optionType":"PE","expiry":"2016-08-25","ts":"NMDC26AUG42PE"},{"symbol":"NMDC","strikePrice":5700,"optionType":"PE","expiry":"2016-07-28","ts":"NMDC26JUL57PE"},{"symbol":"NMDC","strikePrice":4200,"optionType":"CE","expiry":"2016-08-25","ts":"NMDC26AUG42CE"},{"symbol":"NMDC","strikePrice":6600,"optionType":"CE","expiry":"2016-07-28","ts":"NMDC26JUL66CE"},{"symbol":"NMDC","strikePrice":5400,"optionType":"PE","expiry":"2016-07-28","ts":"NMDC26JUL54PE"},{"symbol":"NMDC","strikePrice":6700,"optionType":"PE","expiry":"2016-07-28","ts":"NMDC26JUL67PE"},{"symbol":"NMDC","strikePrice":6600,"optionType":"CE","expiry":"2016-08-25","ts":"NMDC26AUG66CE"},{"symbol":"NMDC","strikePrice":5400,"optionType":"CE","expiry":"2016-07-28","ts":"NMDC26JUL54CE"},{"symbol":"NMDC","strikePrice":6500,"optionType":"PE","expiry":"2016-07-28","ts":"NMDC26JUL65PE"},{"symbol":"NMDC","strikePrice":11300,"optionType":"CE","expiry":"2016-08-25","ts":"NMDC26AUG113CE"},{"symbol":"NMDC","strikePrice":12800,"optionType":"PE","expiry":"2016-08-25","ts":"NMDC26AUG128PE"},{"symbol":"NMDC","strikePrice":5700,"optionType":"CE","expiry":"2016-08-25","ts":"NMDC26AUG57CE"},{"symbol":"NMDC","strikePrice":5700,"optionType":"PE","expiry":"2016-08-25","ts":"NMDC26AUG57PE"},{"symbol":"NMDC","strikePrice":11300,"optionType":"PE","expiry":"2016-08-25","ts":"NMDC26AUG113PE"},{"symbol":"NMDC","strikePrice":11800,"optionType":"PE","expiry":"2016-08-25","ts":"NMDC26AUG118PE"},{"symbol":"NMDC","strikePrice":11800,"optionType":"CE","expiry":"2016-07-28","ts":"NMDC26JUL118CE"},{"symbol":"NMDC","strikePrice":5200,"optionType":"CE","expiry":"2016-08-25","ts":"NMDC26AUG52CE"},{"symbol":"NMDC","strikePrice":5200,"optionType":"CE","expiry":"2016-07-28","ts":"NMDC26JUL52CE"},{"symbol":"NMDC","strikePrice":6700,"optionType":"CE","expiry":"2016-07-28","ts":"NMDC26JUL67CE"},{"symbol":"NMDC","strikePrice":6500,"optionType":"CE","expiry":"2016-07-28","ts":"NMDC26JUL65CE"},{"symbol":"NMDC","strikePrice":5200,"optionType":"PE","expiry":"2016-08-25","ts":"NMDC26AUG52PE"},{"symbol":"NMDC","strikePrice":6600,"optionType":"PE","expiry":"2016-07-28","ts":"NMDC26JUL66PE"},{"symbol":"NMDC","strikePrice":5200,"optionType":"PE","expiry":"2016-07-28","ts":"NMDC26JUL52PE"},{"symbol":"NMDC","strikePrice":6600,"optionType":"PE","expiry":"2016-08-25","ts":"NMDC26AUG66PE"},{"symbol":"NMDC","strikePrice":11300,"optionType":"CE","expiry":"2016-07-28","ts":"NMDC26JUL113CE"},{"symbol":"NMDC","strikePrice":11300,"optionType":"PE","expiry":"2016-07-28","ts":"NMDC26JUL113PE"},{"symbol":"NMDC","strikePrice":11000,"optionType":"CE","expiry":"2016-09-29","ts":"NMDC26SEP110CE"},{"symbol":"NMDC","strikePrice":11000,"optionType":"PE","expiry":"2016-09-29","ts":"NMDC26SEP110PE"},{"symbol":"NMDC","strikePrice":12800,"optionType":"CE","expiry":"2016-07-28","ts":"NMDC26JUL128CE"},{"symbol":"NMDC","strikePrice":12800,"optionType":"PE","expiry":"2016-07-28","ts":"NMDC26JUL128PE"},{"symbol":"NMDC","strikePrice":12800,"optionType":"CE","expiry":"2016-08-25","ts":"NMDC26AUG128CE"},{"symbol":"NMDC","strikePrice":6200,"optionType":"CE","expiry":"2016-07-28","ts":"NMDC26JUL62CE"},{"symbol":"NMDC","strikePrice":11800,"optionType":"CE","expiry":"2016-08-25","ts":"NMDC26AUG118CE"},{"symbol":"NMDC","strikePrice":4200,"optionType":"CE","expiry":"2016-07-28","ts":"NMDC26JUL42CE"},{"symbol":"NMDC","strikePrice":4200,"optionType":"PE","expiry":"2016-07-28","ts":"NMDC26JUL42PE"},{"symbol":"NMDC","strikePrice":11800,"optionType":"PE","expiry":"2016-07-28","ts":"NMDC26JUL118PE"},{"symbol":"NMDC","strikePrice":6100,"optionType":"CE","expiry":"2016-07-28","ts":"NMDC26JUL61CE"},{"symbol":"NMDC","strikePrice":6300,"optionType":"CE","expiry":"2016-07-28","ts":"NMDC26JUL63CE"},{"symbol":"NMDC","strikePrice":6200,"optionType":"PE","expiry":"2016-07-28","ts":"NMDC26JUL62PE"},{"symbol":"NMDC","strikePrice":5000,"optionType":"CE","expiry":"2016-07-28","ts":"NMDC26JUL50CE"},{"symbol":"NMDC","strikePrice":4800,"optionType":"CE","expiry":"2016-08-25","ts":"NMDC26AUG48CE"},{"symbol":"NMDC","strikePrice":6200,"optionType":"PE","expiry":"2016-08-25","ts":"NMDC26AUG62PE"},{"symbol":"NMDC","strikePrice":4800,"optionType":"CE","expiry":"2016-07-28","ts":"NMDC26JUL48CE"},{"symbol":"NMDC","strikePrice":5000,"optionType":"PE","expiry":"2016-07-28","ts":"NMDC26JUL50PE"},{"symbol":"NMDC","strikePrice":6100,"optionType":"PE","expiry":"2016-07-28","ts":"NMDC26JUL61PE"},{"symbol":"NMDC","strikePrice":4800,"optionType":"PE","expiry":"2016-08-25","ts":"NMDC26AUG48PE"},{"symbol":"NMDC","strikePrice":6200,"optionType":"CE","expiry":"2016-08-25","ts":"NMDC26AUG62CE"},{"symbol":"NMDC","strikePrice":6300,"optionType":"PE","expiry":"2016-07-28","ts":"NMDC26JUL63PE"},{"symbol":"NMDC","strikePrice":-1,"optionType":"XX","expiry":"2016-07-28","ts":"NMDC26JULFUT"},{"symbol":"NMDC","strikePrice":-1,"optionType":"XX","expiry":"2016-08-25","ts":"NMDC26AUGFUT"},{"symbol":"NMDC","strikePrice":4800,"optionType":"PE","expiry":"2016-07-28","ts":"NMDC26JUL48PE"},{"symbol":"NMDC","strikePrice":-1,"optionType":"XX","expiry":"2016-09-29","ts":"NMDC26SEPFUT"},{"symbol":"NMDC","strikePrice":8800,"optionType":"PE","expiry":"2026-07-30","ts":"NMDC26JUL88PE"},{"symbol":"NMDC","strikePrice":9700,"optionType":"CE","expiry":"2026-07-30","ts":"NMDC26JUL97CE"},{"symbol":"NMDC","strikePrice":8700,"optionType":"CE","expiry":"2026-07-30","ts":"NMDC26JUL87CE"},{"symbol":"NMDC","strikePrice":9400,"optionType":"PE","expiry":"2026-07-30","ts":"NMDC26JUL94PE"},{"symbol":"NMDC","strikePrice":9000,"optionType":"CE","expiry":"2026-07-30","ts":"NMDC26JUL90CE"},{"symbol":"NMDC","strikePrice":9000,"optionType":"PE","expiry":"2026-07-30","ts":"NMDC26JUL90PE"},{"symbol":"NMDC","strikePrice":8300,"optionType":"PE","expiry":"2026-07-30","ts":"NMDC26JUL83PE"},{"symbol":"NMDC","strikePrice":8300,"optionType":"CE","expiry":"2026-07-30","ts":"NMDC26JUL83CE"},{"symbol":"NMDC","strikePrice":8700,"optionType":"PE","expiry":"2026-07-30","ts":"NMDC26JUL87PE"},{"symbol":"NMDC","strikePrice":9300,"optionType":"PE","expiry":"2026-07-30","ts":"NMDC26JUL93PE"},{"symbol":"NMDC","strikePrice":9200,"optionType":"CE","expiry":"2026-07-30","ts":"NMDC26JUL92CE"},{"symbol":"NMDC","strikePrice":9600,"optionType":"PE","expiry":"2026-07-30","ts":"NMDC26JUL96PE"},{"symbol":"NMDC","strikePrice":0,"optionType":"XX","expiry":"2026-07-30","ts":"NMDC26JULFUT"},{"symbol":"NMDC","strikePrice":8600,"optionType":"PE","expiry":"2026-07-30","ts":"NMDC26JUL86PE"},{"symbol":"NMDC","strikePrice":9200,"optionType":"PE","expiry":"2026-07-30","ts":"NMDC26JUL92PE"},{"symbol":"NMDC","strikePrice":9700,"optionType":"PE","expiry":"2026-07-30","ts":"NMDC26JUL97PE"},{"symbol":"NMDC","strikePrice":8600,"optionType":"CE","expiry":"2026-07-30","ts":"NMDC26JUL86CE"},{"symbol":"NMDC","strikePrice":8900,"optionType":"CE","expiry":"2026-07-30","ts":"NMDC26JUL89CE"},{"symbol":"NMDC","strikePrice":9500,"optionType":"CE","expiry":"2026-07-30","ts":"NMDC26JUL95CE"},{"symbol":"NMDC","strikePrice":9500,"optionType":"PE","expiry":"2026-07-30","ts":"NMDC26JUL95PE"},{"symbol":"NMDC","strikePrice":8000,"optionType":"PE","expiry":"2026-07-30","ts":"NMDC26JUL80PE"},{"symbol":"NMDC","strikePrice":8100,"optionType":"CE","expiry":"2026-07-30","ts":"NMDC26JUL81CE"},{"symbol":"NMDC","strikePrice":8900,"optionType":"PE","expiry":"2026-07-30","ts":"NMDC26JUL89PE"},{"symbol":"NMDC","strikePrice":9300,"optionType":"CE","expiry":"2026-07-30","ts":"NMDC26JUL93CE"},{"symbol":"NMDC","strikePrice":8500,"optionType":"CE","expiry":"2026-07-30","ts":"NMDC26JUL85CE"},{"symbol":"NMDC","strikePrice":9100,"optionType":"CE","expiry":"2026-07-30","ts":"NMDC26JUL91CE"},{"symbol":"NMDC","strikePrice":9600,"optionType":"CE","expiry":"2026-07-30","ts":"NMDC26JUL96CE"},{"symbol":"NMDC","strikePrice":8200,"optionType":"CE","expiry":"2026-07-30","ts":"NMDC26JUL82CE"},{"symbol":"NMDC","strikePrice":9400,"optionType":"CE","expiry":"2026-07-30","ts":"NMDC26JUL94CE"},{"symbol":"NMDC","strikePrice":8100,"optionType":"PE","expiry":"2026-07-30","ts":"NMDC26JUL81PE"},{"symbol":"NMDC","strikePrice":8400,"optionType":"CE","expiry":"2026-07-30","ts":"NMDC26JUL84CE"},{"symbol":"NMDC","strikePrice":8200,"optionType":"PE","expiry":"2026-07-30","ts":"NMDC26JUL82PE"},{"symbol":"NMDC","strikePrice":8500,"optionType":"PE","expiry":"2026-07-30","ts":"NMDC26JUL85PE"},{"symbol":"NMDC","strikePrice":9100,"optionType":"PE","expiry":"2026-07-30","ts":"NMDC26JUL91PE"},{"symbol":"NMDC","strikePrice":8000,"optionType":"CE","expiry":"2026-07-30","ts":"NMDC26JUL80CE"},{"symbol":"NMDC","strikePrice":8400,"optionType":"PE","expiry":"2026-07-30","ts":"NMDC26JUL84PE"},{"symbol":"NMDC","strikePrice":8800,"optionType":"CE","expiry":"2026-07-30","ts":"NMDC26JUL88CE"},{"symbol":"NMDC","strikePrice":9900,"optionType":"PE","expiry":"2026-08-27","ts":"NMDC26AUG99PE"},{"symbol":"NMDC","strikePrice":9200,"optionType":"PE","expiry":"2026-08-27","ts":"NMDC26AUG92PE"},{"symbol":"NMDC","strikePrice":9500,"optionType":"PE","expiry":"2026-08-27","ts":"NMDC26AUG95PE"},{"symbol":"NMDC","strikePrice":0,"optionType":"XX","expiry":"2026-08-27","ts":"NMDC26AUGFUT"},{"symbol":"NMDC","strikePrice":9200,"optionType":"CE","expiry":"2026-08-27","ts":"NMDC26AUG92CE"},{"symbol":"NMDC","strikePrice":8600,"optionType":"PE","expiry":"2026-08-27","ts":"NMDC26AUG86PE"},{"symbol":"NMDC","strikePrice":9800,"optionType":"PE","expiry":"2026-08-27","ts":"NMDC26AUG98PE"},{"symbol":"NMDC","strikePrice":10000,"optionType":"CE","expiry":"2026-07-30","ts":"NMDC26JUL100CE"},{"symbol":"NMDC","strikePrice":9800,"optionType":"CE","expiry":"2026-07-30","ts":"NMDC26JUL98CE"},{"symbol":"NMDC","strikePrice":9600,"optionType":"PE","expiry":"2026-08-27","ts":"NMDC26AUG96PE"},{"symbol":"NMDC","strikePrice":8900,"optionType":"PE","expiry":"2026-08-27","ts":"NMDC26AUG89PE"},{"symbol":"NMDC","strikePrice":9400,"optionType":"PE","expiry":"2026-08-27","ts":"NMDC26AUG94PE"},{"symbol":"NMDC","strikePrice":9400,"optionType":"CE","expiry":"2026-08-27","ts":"NMDC26AUG94CE"},{"symbol":"NMDC","strikePrice":8800,"optionType":"PE","expiry":"2026-08-27","ts":"NMDC26AUG88PE"},{"symbol":"NMDC","strikePrice":9700,"optionType":"CE","expiry":"2026-08-27","ts":"NMDC26AUG97CE"},{"symbol":"NMDC","strikePrice":8500,"optionType":"CE","expiry":"2026-08-27","ts":"NMDC26AUG85CE"},{"symbol":"NMDC","strikePrice":9700,"optionType":"PE","expiry":"2026-08-27","ts":"NMDC26AUG97PE"},{"symbol":"NMDC","strikePrice":9300,"optionType":"PE","expiry":"2026-08-27","ts":"NMDC26AUG93PE"},{"symbol":"NMDC","strikePrice":9000,"optionType":"CE","expiry":"2026-08-27","ts":"NMDC26AUG90CE"},{"symbol":"NMDC","strikePrice":9500,"optionType":"CE","expiry":"2026-08-27","ts":"NMDC26AUG95CE"},{"symbol":"NMDC","strikePrice":8800,"optionType":"CE","expiry":"2026-08-27","ts":"NMDC26AUG88CE"},{"symbol":"NMDC","strikePrice":9900,"optionType":"PE","expiry":"2026-07-30","ts":"NMDC26JUL99PE"},{"symbol":"NMDC","strikePrice":9800,"optionType":"PE","expiry":"2026-07-30","ts":"NMDC26JUL98PE"},{"symbol":"NMDC","strikePrice":9900,"optionType":"CE","expiry":"2026-07-30","ts":"NMDC26JUL99CE"},{"symbol":"NMDC","strikePrice":9100,"optionType":"PE","expiry":"2026-08-27","ts":"NMDC26AUG91PE"},{"symbol":"NMDC","strikePrice":8900,"optionType":"CE","expiry":"2026-08-27","ts":"NMDC26AUG89CE"},{"symbol":"NMDC","strikePrice":8700,"optionType":"CE","expiry":"2026-08-27","ts":"NMDC26AUG87CE"},{"symbol":"NMDC","strikePrice":8700,"optionType":"PE","expiry":"2026-08-27","ts":"NMDC26AUG87PE"},{"symbol":"NMDC","strikePrice":9000,"optionType":"PE","expiry":"2026-08-27","ts":"NMDC26AUG90PE"},{"symbol":"NMDC","strikePrice":10200,"optionType":"CE","expiry":"2026-07-30","ts":"NMDC26JUL102CE"},{"symbol":"NMDC","strikePrice":8700,"optionType":"PE","expiry":"2026-09-24","ts":"NMDC26SEP87PE"},{"symbol":"NMDC","strikePrice":7800,"optionType":"CE","expiry":"2026-09-24","ts":"NMDC26SEP78CE"},{"symbol":"NMDC","strikePrice":8200,"optionType":"PE","expiry":"2026-09-24","ts":"NMDC26SEP82PE"},{"symbol":"NMDC","strikePrice":8600,"optionType":"CE","expiry":"2026-09-24","ts":"NMDC26SEP86CE"},{"symbol":"NMDC","strikePrice":8400,"optionType":"PE","expiry":"2026-08-27","ts":"NMDC26AUG84PE"},{"symbol":"NMDC","strikePrice":7900,"optionType":"CE","expiry":"2026-09-24","ts":"NMDC26SEP79CE"},{"symbol":"NMDC","strikePrice":10200,"optionType":"PE","expiry":"2026-07-30","ts":"NMDC26JUL102PE"},{"symbol":"NMDC","strikePrice":10200,"optionType":"PE","expiry":"2026-08-27","ts":"NMDC26AUG102PE"},{"symbol":"NMDC","strikePrice":9000,"optionType":"CE","expiry":"2026-09-24","ts":"NMDC26SEP90CE"},{"symbol":"NMDC","strikePrice":8200,"optionType":"PE","expiry":"2026-08-27","ts":"NMDC26AUG82PE"},{"symbol":"NMDC","strikePrice":9200,"optionType":"PE","expiry":"2026-09-24","ts":"NMDC26SEP92PE"},{"symbol":"NMDC","strikePrice":10000,"optionType":"PE","expiry":"2026-08-27","ts":"NMDC26AUG100PE"},{"symbol":"NMDC","strikePrice":8100,"optionType":"CE","expiry":"2026-08-27","ts":"NMDC26AUG81CE"},{"symbol":"NMDC","strikePrice":8300,"optionType":"PE","expiry":"2026-08-27","ts":"NMDC26AUG83PE"},{"symbol":"NMDC","strikePrice":0,"optionType":"XX","expiry":"2026-09-24","ts":"NMDC26SEPFUT"},{"symbol":"NMDC","strikePrice":8300,"optionType":"PE","expiry":"2026-09-24","ts":"NMDC26SEP83PE"},{"symbol":"NMDC","strikePrice":8800,"optionType":"PE","expiry":"2026-09-24","ts":"NMDC26SEP88PE"},{"symbol":"NMDC","strikePrice":8400,"optionType":"CE","expiry":"2026-08-27","ts":"NMDC26AUG84CE"},{"symbol":"NMDC","strikePrice":8100,"optionType":"CE","expiry":"2026-09-24","ts":"NMDC26SEP81CE"},{"symbol":"NMDC","strikePrice":7800,"optionType":"PE","expiry":"2026-09-24","ts":"NMDC26SEP78PE"},{"symbol":"NMDC","strikePrice":8900,"optionType":"CE","expiry":"2026-09-24","ts":"NMDC26SEP89CE"},{"symbol":"NMDC","strikePrice":9800,"optionType":"CE","expiry":"2026-08-27","ts":"NMDC26AUG98CE"},{"symbol":"NMDC","strikePrice":9100,"optionType":"CE","expiry":"2026-09-24","ts":"NMDC26SEP91CE"},{"symbol":"NMDC","strikePrice":7900,"optionType":"PE","expiry":"2026-09-24","ts":"NMDC26SEP79PE"},{"symbol":"NMDC","strikePrice":9300,"optionType":"PE","expiry":"2026-09-24","ts":"NMDC26SEP93PE"},{"symbol":"NMDC","strikePrice":7900,"optionType":"CE","expiry":"2026-08-27","ts":"NMDC26AUG79CE"},{"symbol":"NMDC","strikePrice":7800,"optionType":"CE","expiry":"2026-07-30","ts":"NMDC26JUL78CE"},{"symbol":"NMDC","strikePrice":7800,"optionType":"CE","expiry":"2026-08-27","ts":"NMDC26AUG78CE"},{"symbol":"NMDC","strikePrice":9300,"optionType":"CE","expiry":"2026-08-27","ts":"NMDC26AUG93CE"},{"symbol":"NMDC","strikePrice":8700,"optionType":"CE","expiry":"2026-09-24","ts":"NMDC26SEP87CE"},{"symbol":"NMDC","strikePrice":8200,"optionType":"CE","expiry":"2026-09-24","ts":"NMDC26SEP82CE"},{"symbol":"NMDC","strikePrice":8100,"optionType":"PE","expiry":"2026-09-24","ts":"NMDC26SEP81PE"},{"symbol":"NMDC","strikePrice":8600,"optionType":"PE","expiry":"2026-09-24","ts":"NMDC26SEP86PE"},{"symbol":"NMDC","strikePrice":9100,"optionType":"CE","expiry":"2026-08-27","ts":"NMDC26AUG91CE"},{"symbol":"NMDC","strikePrice":9600,"optionType":"CE","expiry":"2026-08-27","ts":"NMDC26AUG96CE"},{"symbol":"NMDC","strikePrice":9900,"optionType":"CE","expiry":"2026-08-27","ts":"NMDC26AUG99CE"},{"symbol":"NMDC","strikePrice":8500,"optionType":"PE","expiry":"2026-08-27","ts":"NMDC26AUG85PE"},{"symbol":"NMDC","strikePrice":8400,"optionType":"PE","expiry":"2026-09-24","ts":"NMDC26SEP84PE"},{"symbol":"NMDC","strikePrice":10300,"optionType":"CE","expiry":"2026-08-27","ts":"NMDC26AUG103CE"},{"symbol":"NMDC","strikePrice":9100,"optionType":"PE","expiry":"2026-09-24","ts":"NMDC26SEP91PE"},{"symbol":"NMDC","strikePrice":8100,"optionType":"PE","expiry":"2026-08-27","ts":"NMDC26AUG81PE"},{"symbol":"NMDC","strikePrice":10000,"optionType":"PE","expiry":"2026-07-30","ts":"NMDC26JUL100PE"},{"symbol":"NMDC","strikePrice":8600,"optionType":"CE","expiry":"2026-08-27","ts":"NMDC26AUG86CE"},{"symbol":"NMDC","strikePrice":8000,"optionType":"PE","expiry":"2026-09-24","ts":"NMDC26SEP80PE"},{"symbol":"NMDC","strikePrice":8400,"optionType":"CE","expiry":"2026-09-24","ts":"NMDC26SEP84CE"},{"symbol":"NMDC","strikePrice":8300,"optionType":"CE","expiry":"2026-08-27","ts":"NMDC26AUG83CE"},{"symbol":"NMDC","strikePrice":7700,"optionType":"PE","expiry":"2026-07-30","ts":"NMDC26JUL77PE"},{"symbol":"NMDC","strikePrice":7700,"optionType":"PE","expiry":"2026-08-27","ts":"NMDC26AUG77PE"},{"symbol":"NMDC","strikePrice":7900,"optionType":"CE","expiry":"2026-07-30","ts":"NMDC26JUL79CE"},{"symbol":"NMDC","strikePrice":7800,"optionType":"PE","expiry":"2026-08-27","ts":"NMDC26AUG78PE"},{"symbol":"NMDC","strikePrice":7800,"optionType":"PE","expiry":"2026-07-30","ts":"NMDC26JUL78PE"},{"symbol":"NMDC","strikePrice":8000,"optionType":"PE","expiry":"2026-08-27","ts":"NMDC26AUG80PE"},{"symbol":"NMDC","strikePrice":7900,"optionType":"PE","expiry":"2026-08-27","ts":"NMDC26AUG79PE"},{"symbol":"NMDC","strikePrice":8900,"optionType":"PE","expiry":"2026-09-24","ts":"NMDC26SEP89PE"},{"symbol":"NMDC","strikePrice":8500,"optionType":"CE","expiry":"2026-09-24","ts":"NMDC26SEP85CE"},{"symbol":"NMDC","strikePrice":10300,"optionType":"PE","expiry":"2026-07-30","ts":"NMDC26JUL103PE"},{"symbol":"NMDC","strikePrice":10100,"optionType":"PE","expiry":"2026-08-27","ts":"NMDC26AUG101PE"},{"symbol":"NMDC","strikePrice":10300,"optionType":"PE","expiry":"2026-08-27","ts":"NMDC26AUG103PE"},{"symbol":"NMDC","strikePrice":8000,"optionType":"CE","expiry":"2026-09-24","ts":"NMDC26SEP80CE"},{"symbol":"NMDC","strikePrice":10100,"optionType":"PE","expiry":"2026-07-30","ts":"NMDC26JUL101PE"},{"symbol":"NMDC","strikePrice":10100,"optionType":"CE","expiry":"2026-08-27","ts":"NMDC26AUG101CE"},{"symbol":"NMDC","strikePrice":8200,"optionType":"CE","expiry":"2026-08-27","ts":"NMDC26AUG82CE"},{"symbol":"NMDC","strikePrice":8500,"optionType":"PE","expiry":"2026-09-24","ts":"NMDC26SEP85PE"},{"symbol":"NMDC","strikePrice":7700,"optionType":"CE","expiry":"2026-08-27","ts":"NMDC26AUG77CE"},{"symbol":"NMDC","strikePrice":9200,"optionType":"CE","expiry":"2026-09-24","ts":"NMDC26SEP92CE"},{"symbol":"NMDC","strikePrice":9300,"optionType":"CE","expiry":"2026-09-24","ts":"NMDC26SEP93CE"},{"symbol":"NMDC","strikePrice":8300,"optionType":"CE","expiry":"2026-09-24","ts":"NMDC26SEP83CE"},{"symbol":"NMDC","strikePrice":10300,"optionType":"CE","expiry":"2026-07-30","ts":"NMDC26JUL103CE"},{"symbol":"NMDC","strikePrice":10200,"optionType":"CE","expiry":"2026-08-27","ts":"NMDC26AUG102CE"},{"symbol":"NMDC","strikePrice":10100,"optionType":"CE","expiry":"2026-07-30","ts":"NMDC26JUL101CE"},{"symbol":"NMDC","strikePrice":8800,"optionType":"CE","expiry":"2026-09-24","ts":"NMDC26SEP88CE"},{"symbol":"NMDC","strikePrice":10000,"optionType":"CE","expiry":"2026-08-27","ts":"NMDC26AUG100CE"},{"symbol":"NMDC","strikePrice":7700,"optionType":"CE","expiry":"2026-09-24","ts":"NMDC26SEP77CE"},{"symbol":"NMDC","strikePrice":9000,"optionType":"PE","expiry":"2026-09-24","ts":"NMDC26SEP90PE"},{"symbol":"NMDC","strikePrice":7700,"optionType":"CE","expiry":"2026-07-30","ts":"NMDC26JUL77CE"},{"symbol":"NMDC","strikePrice":7700,"optionType":"PE","expiry":"2026-09-24","ts":"NMDC26SEP77PE"},{"symbol":"NMDC","strikePrice":7900,"optionType":"PE","expiry":"2026-07-30","ts":"NMDC26JUL79PE"},{"symbol":"NMDC","strikePrice":8000,"optionType":"CE","expiry":"2026-08-27","ts":"NMDC26AUG80CE"}]