[{"symbol":"NTPC","strikePrice":28250,"optionType":"PE","expiry":"2016-03-30","ts":"NTPC26MAR282.5PE"},{"symbol":"NTPC","strikePrice":32000,"optionType":"CE","expiry":"2016-03-30","ts":"NTPC26MAR320CE"},{"symbol":"NTPC","strikePrice":42250,"optionType":"CE","expiry":"2016-02-25","ts":"NTPC26FEB422.5CE"},{"symbol":"NTPC","strikePrice":19000,"optionType":"CE","expiry":"2016-04-28","ts":"NTPC26APR190CE"},{"symbol":"NTPC","strikePrice":42500,"optionType":"PE","expiry":"2016-02-25","ts":"NTPC26FEB425PE"},{"symbol":"NTPC","strikePrice":30500,"optionType":"PE","expiry":"2016-04-28","ts":"NTPC26APR305PE"},{"symbol":"NTPC","strikePrice":38250,"optionType":"PE","expiry":"2016-02-25","ts":"NTPC26FEB382.5PE"},{"symbol":"NTPC","strikePrice":39500,"optionType":"CE","expiry":"2016-04-28","ts":"NTPC26APR395CE"},{"symbol":"NTPC","strikePrice":42500,"optionType":"CE","expiry":"2016-03-30","ts":"NTPC26MAR425CE"},{"symbol":"NTPC","strikePrice":-1,"optionType":"XX","expiry":"2016-02-25","ts":"NTPC26FEBFUT"},{"symbol":"NTPC","strikePrice":42250,"optionType":"CE","expiry":"2016-03-30","ts":"NTPC26MAR422.5CE"},{"symbol":"NTPC","strikePrice":26750,"optionType":"CE","expiry":"2016-02-25","ts":"NTPC26FEB267.5CE"},{"symbol":"NTPC","strikePrice":44000,"optionType":"CE","expiry":"2016-04-28","ts":"NTPC26APR440CE"},{"symbol":"NTPC","strikePrice":46500,"optionType":"CE","expiry":"2016-02-25","ts":"NTPC26FEB465CE"},{"symbol":"NTPC","strikePrice":29000,"optionType":"PE","expiry":"2016-02-25","ts":"NTPC26FEB290PE"},{"symbol":"NTPC","strikePrice":38000,"optionType":"PE","expiry":"2016-02-25","ts":"NTPC26FEB380PE"},{"symbol":"NTPC","strikePrice":35000,"optionType":"PE","expiry":"2016-02-25","ts":"NTPC26FEB350PE"},{"symbol":"NTPC","strikePrice":32750,"optionType":"PE","expiry":"2016-03-30","ts":"NTPC26MAR327.5PE"},{"symbol":"NTPC","strikePrice":34500,"optionType":"PE","expiry":"2016-02-25","ts":"NTPC26FEB345PE"},{"symbol":"NTPC","strikePrice":44500,"optionType":"PE","expiry":"2016-03-30","ts":"NTPC26MAR445PE"},{"symbol":"NTPC","strikePrice":33500,"optionType":"PE","expiry":"2016-02-25","ts":"NTPC26FEB335PE"},{"symbol":"NTPC","strikePrice":39500,"optionType":"CE","expiry":"2016-03-30","ts":"NTPC26MAR395CE"},{"symbol":"NTPC","strikePrice":45000,"optionType":"CE","expiry":"2016-04-28","ts":"NTPC26APR450CE"},{"symbol":"NTPC","strikePrice":29750,"optionType":"PE","expiry":"2016-03-30","ts":"NTPC26MAR297.5PE"},{"symbol":"NTPC","strikePrice":45000,"optionType":"CE","expiry":"2016-03-30","ts":"NTPC26MAR450CE"},{"symbol":"NTPC","strikePrice":40500,"optionType":"PE","expiry":"2016-03-30","ts":"NTPC26MAR405PE"},{"symbol":"NTPC","strikePrice":32250,"optionType":"CE","expiry":"2016-03-30","ts":"NTPC26MAR322.5CE"},{"symbol":"NTPC","strikePrice":34000,"optionType":"CE","expiry":"2016-03-30","ts":"NTPC26MAR340CE"},{"symbol":"NTPC","strikePrice":43000,"optionType":"PE","expiry":"2016-03-30","ts":"NTPC26MAR430PE"},{"symbol":"NTPC","strikePrice":44500,"optionType":"CE","expiry":"2016-03-30","ts":"NTPC26MAR445CE"},{"symbol":"NTPC","strikePrice":23500,"optionType":"PE","expiry":"2016-03-30","ts":"NTPC26MAR235PE"},{"symbol":"NTPC","strikePrice":22000,"optionType":"PE","expiry":"2016-02-25","ts":"NTPC26FEB220PE"},{"symbol":"NTPC","strikePrice":47000,"optionType":"CE","expiry":"2016-04-28","ts":"NTPC26APR470CE"},{"symbol":"NTPC","strikePrice":44250,"optionType":"CE","expiry":"2016-02-25","ts":"NTPC26FEB442.5CE"},{"symbol":"NTPC","strikePrice":32500,"optionType":"CE","expiry":"2016-02-25","ts":"NTPC26FEB325CE"},{"symbol":"NTPC","strikePrice":28500,"optionType":"CE","expiry":"2016-04-28","ts":"NTPC26APR285CE"},{"symbol":"NTPC","strikePrice":28250,"optionType":"CE","expiry":"2016-02-25","ts":"NTPC26FEB282.5CE"},{"symbol":"NTPC","strikePrice":19500,"optionType":"PE","expiry":"2016-02-25","ts":"NTPC26FEB195PE"},{"symbol":"NTPC","strikePrice":37250,"optionType":"PE","expiry":"2016-02-25","ts":"NTPC26FEB372.5PE"},{"symbol":"NTPC","strikePrice":45500,"optionType":"CE","expiry":"2016-02-25","ts":"NTPC26FEB455CE"},{"symbol":"NTPC","strikePrice":25500,"optionType":"PE","expiry":"2016-02-25","ts":"NTPC26FEB255PE"},{"symbol":"NTPC","strikePrice":22000,"optionType":"PE","expiry":"2016-03-30","ts":"NTPC26MAR220PE"},{"symbol":"NTPC","strikePrice":44750,"optionType":"PE","expiry":"2016-03-30","ts":"NTPC26MAR447.5PE"},{"symbol":"NTPC","strikePrice":30750,"optionType":"PE","expiry":"2016-03-30","ts":"NTPC26MAR307.5PE"},{"symbol":"NTPC","strikePrice":29000,"optionType":"CE","expiry":"2016-02-25","ts":"NTPC26FEB290CE"},{"symbol":"NTPC","strikePrice":35750,"optionType":"CE","expiry":"2016-03-30","ts":"NTPC26MAR357.5CE"},{"symbol":"NTPC","strikePrice":43500,"optionType":"PE","expiry":"2016-04-28","ts":"NTPC26APR435PE"},{"symbol":"NTPC","strikePrice":32750,"optionType":"CE","expiry":"2016-03-30","ts":"NTPC26MAR327.5CE"},{"symbol":"NTPC","strikePrice":44250,"optionType":"CE","expiry":"2016-03-30","ts":"NTPC26MAR442.5CE"},{"symbol":"NTPC","strikePrice":25000,"optionType":"PE","expiry":"2016-02-25","ts":"NTPC26FEB250PE"},{"symbol":"NTPC","strikePrice":24000,"optionType":"CE","expiry":"2016-02-25","ts":"NTPC26FEB240CE"},{"symbol":"NTPC","strikePrice":48000,"optionType":"CE","expiry":"2016-04-28","ts":"NTPC26APR480CE"},{"symbol":"NTPC","strikePrice":32250,"optionType":"PE","expiry":"2016-02-25","ts":"NTPC26FEB322.5PE"},{"symbol":"NTPC","strikePrice":29250,"optionType":"CE","expiry":"2016-02-25","ts":"NTPC26FEB292.5CE"},{"symbol":"NTPC","strikePrice":21500,"optionType":"PE","expiry":"2016-03-30","ts":"NTPC26MAR215PE"},{"symbol":"NTPC","strikePrice":41250,"optionType":"PE","expiry":"2016-02-25","ts":"NTPC26FEB412.5PE"},{"symbol":"NTPC","strikePrice":32750,"optionType":"CE","expiry":"2016-02-25","ts":"NTPC26FEB327.5CE"},{"symbol":"NTPC","strikePrice":31500,"optionType":"CE","expiry":"2016-02-25","ts":"NTPC26FEB315CE"},{"symbol":"NTPC","strikePrice":39250,"optionType":"CE","expiry":"2016-03-30","ts":"NTPC26MAR392.5CE"},{"symbol":"NTPC","strikePrice":34500,"optionType":"CE","expiry":"2016-04-28","ts":"NTPC26APR345CE"},{"symbol":"NTPC","strikePrice":19500,"optionType":"PE","expiry":"2016-03-30","ts":"NTPC26MAR195PE"},{"symbol":"NTPC","strikePrice":49500,"optionType":"PE","expiry":"2016-02-25","ts":"NTPC26FEB495PE"},{"symbol":"NTPC","strikePrice":31250,"optionType":"CE","expiry":"2016-03-30","ts":"NTPC26MAR312.5CE"},{"symbol":"NTPC","strikePrice":45250,"optionType":"PE","expiry":"2016-03-30","ts":"NTPC26MAR452.5PE"},{"symbol":"NTPC","strikePrice":51500,"optionType":"CE","expiry":"2016-03-30","ts":"NTPC26MAR515CE"},{"symbol":"NTPC","strikePrice":50500,"optionType":"PE","expiry":"2016-03-30","ts":"NTPC26MAR505PE"},{"symbol":"NTPC","strikePrice":34500,"optionType":"PE","expiry":"2016-03-30","ts":"NTPC26MAR345PE"},{"symbol":"NTPC","strikePrice":47500,"optionType":"CE","expiry":"2016-02-25","ts":"NTPC26FEB475CE"},{"symbol":"NTPC","strikePrice":38250,"optionType":"PE","expiry":"2016-03-30","ts":"NTPC26MAR382.5PE"},{"symbol":"NTPC","strikePrice":25500,"optionType":"CE","expiry":"2016-03-30","ts":"NTPC26MAR255CE"},{"symbol":"NTPC","strikePrice":35750,"optionType":"PE","expiry":"2016-02-25","ts":"NTPC26FEB357.5PE"},{"symbol":"NTPC","strikePrice":45000,"optionType":"PE","expiry":"2016-03-30","ts":"NTPC26MAR450PE"},{"symbol":"NTPC","strikePrice":50500,"optionType":"PE","expiry":"2016-02-25","ts":"NTPC26FEB505PE"},{"symbol":"NTPC","strikePrice":30250,"optionType":"PE","expiry":"2016-02-25","ts":"NTPC26FEB302.5PE"},{"symbol":"NTPC","strikePrice":43500,"optionType":"CE","expiry":"2016-03-30","ts":"NTPC26MAR435CE"},{"symbol":"NTPC","strikePrice":47500,"optionType":"PE","expiry":"2016-03-30","ts":"NTPC26MAR475PE"},{"symbol":"NTPC","strikePrice":40250,"optionType":"PE","expiry":"2016-02-25","ts":"NTPC26FEB402.5PE"},{"symbol":"NTPC","strikePrice":29250,"optionType":"PE","expiry":"2016-02-25","ts":"NTPC26FEB292.5PE"},{"symbol":"NTPC","strikePrice":36750,"optionType":"CE","expiry":"2016-03-30","ts":"NTPC26MAR367.5CE"},{"symbol":"NTPC","strikePrice":26500,"optionType":"CE","expiry":"2016-04-28","ts":"NTPC26APR265CE"},{"symbol":"NTPC","strikePrice":39750,"optionType":"PE","expiry":"2016-02-25","ts":"NTPC26FEB397.5PE"},{"symbol":"NTPC","strikePrice":22000,"optionType":"CE","expiry":"2016-02-25","ts":"NTPC26FEB220CE"},{"symbol":"NTPC","strikePrice":29000,"optionType":"PE","expiry":"2016-03-30","ts":"NTPC26MAR290PE"},{"symbol":"NTPC","strikePrice":35250,"optionType":"CE","expiry":"2016-02-25","ts":"NTPC26FEB352.5CE"},{"symbol":"NTPC","strikePrice":26000,"optionType":"PE","expiry":"2016-03-30","ts":"NTPC26MAR260PE"},{"symbol":"NTPC","strikePrice":51500,"optionType":"PE","expiry":"2016-03-30","ts":"NTPC26MAR515PE"},{"symbol":"NTPC","strikePrice":42000,"optionType":"CE","expiry":"2016-04-28","ts":"NTPC26APR420CE"},{"symbol":"NTPC","strikePrice":34000,"optionType":"CE","expiry":"2016-02-25","ts":"NTPC26FEB340CE"},{"symbol":"NTPC","strikePrice":43250,"optionType":"PE","expiry":"2016-03-30","ts":"NTPC26MAR432.5PE"},{"symbol":"NTPC","strikePrice":26000,"optionType":"PE","expiry":"2016-04-28","ts":"NTPC26APR260PE"},{"symbol":"NTPC","strikePrice":32500,"optionType":"PE","expiry":"2016-02-25","ts":"NTPC26FEB325PE"},{"symbol":"NTPC","strikePrice":28000,"optionType":"CE","expiry":"2016-03-30","ts":"NTPC26MAR280CE"},{"symbol":"NTPC","strikePrice":42750,"optionType":"PE","expiry":"2016-02-25","ts":"NTPC26FEB427.5PE"},{"symbol":"NTPC","strikePrice":45000,"optionType":"CE","expiry":"2016-02-25","ts":"NTPC26FEB450CE"},{"symbol":"NTPC","strikePrice":35500,"optionType":"CE","expiry":"2016-04-28","ts":"NTPC26APR355CE"},{"symbol":"NTPC","strikePrice":45500,"optionType":"PE","expiry":"2016-02-25","ts":"NTPC26FEB455PE"},{"symbol":"NTPC","strikePrice":41750,"optionType":"CE","expiry":"2016-02-25","ts":"NTPC26FEB417.5CE"},{"symbol":"NTPC","strikePrice":41000,"optionType":"CE","expiry":"2016-03-30","ts":"NTPC26MAR410CE"},{"symbol":"NTPC","strikePrice":23000,"optionType":"PE","expiry":"2016-03-30","ts":"NTPC26MAR230PE"},{"symbol":"NTPC","strikePrice":40750,"optionType":"PE","expiry":"2016-02-25","ts":"NTPC26FEB407.5PE"},{"symbol":"NTPC","strikePrice":33500,"optionType":"CE","expiry":"2016-03-30","ts":"NTPC26MAR335CE"},{"symbol":"NTPC","strikePrice":38750,"optionType":"PE","expiry":"2016-02-25","ts":"NTPC26FEB387.5PE"},{"symbol":"NTPC","strikePrice":30000,"optionType":"PE","expiry":"2016-03-30","ts":"NTPC26MAR300PE"},{"symbol":"NTPC","strikePrice":47000,"optionType":"CE","expiry":"2016-03-30","ts":"NTPC26MAR470CE"},{"symbol":"NTPC","strikePrice":31500,"optionType":"CE","expiry":"2016-04-28","ts":"NTPC26APR315CE"},{"symbol":"NTPC","strikePrice":23000,"optionType":"CE","expiry":"2016-03-30","ts":"NTPC26MAR230CE"},{"symbol":"NTPC","strikePrice":39500,"optionType":"PE","expiry":"2016-03-30","ts":"NTPC26MAR395PE"},{"symbol":"NTPC","strikePrice":37000,"optionType":"PE","expiry":"2016-04-28","ts":"NTPC26APR370PE"},{"symbol":"NTPC","strikePrice":27000,"optionType":"CE","expiry":"2016-04-28","ts":"NTPC26APR270CE"},{"symbol":"NTPC","strikePrice":40500,"optionType":"PE","expiry":"2016-04-28","ts":"NTPC26APR405PE"},{"symbol":"NTPC","strikePrice":42500,"optionType":"CE","expiry":"2016-02-25","ts":"NTPC26FEB425CE"},{"symbol":"NTPC","strikePrice":35250,"optionType":"PE","expiry":"2016-02-25","ts":"NTPC26FEB352.5PE"},{"symbol":"NTPC","strikePrice":25000,"optionType":"CE","expiry":"2016-04-28","ts":"NTPC26APR250CE"},{"symbol":"NTPC","strikePrice":51000,"optionType":"PE","expiry":"2016-04-28","ts":"NTPC26APR510PE"},{"symbol":"NTPC","strikePrice":28750,"optionType":"CE","expiry":"2016-02-25","ts":"NTPC26FEB287.5CE"},{"symbol":"NTPC","strikePrice":21500,"optionType":"CE","expiry":"2016-03-30","ts":"NTPC26MAR215CE"},{"symbol":"NTPC","strikePrice":49000,"optionType":"PE","expiry":"2016-02-25","ts":"NTPC26FEB490PE"},{"symbol":"NTPC","strikePrice":36500,"optionType":"PE","expiry":"2016-04-28","ts":"NTPC26APR365PE"},{"symbol":"NTPC","strikePrice":43750,"optionType":"PE","expiry":"2016-03-30","ts":"NTPC26MAR437.5PE"},{"symbol":"NTPC","strikePrice":31000,"optionType":"PE","expiry":"2016-04-28","ts":"NTPC26APR310PE"},{"symbol":"NTPC","strikePrice":25000,"optionType":"PE","expiry":"2016-03-30","ts":"NTPC26MAR250PE"},{"symbol":"NTPC","strikePrice":45250,"optionType":"PE","expiry":"2016-02-25","ts":"NTPC26FEB452.5PE"},{"symbol":"NTPC","strikePrice":34500,"optionType":"CE","expiry":"2016-03-30","ts":"NTPC26MAR345CE"},{"symbol":"NTPC","strikePrice":50500,"optionType":"CE","expiry":"2016-02-25","ts":"NTPC26FEB505CE"},{"symbol":"NTPC","strikePrice":26000,"optionType":"CE","expiry":"2016-03-30","ts":"NTPC26MAR260CE"},{"symbol":"NTPC","strikePrice":33500,"optionType":"PE","expiry":"2016-03-30","ts":"NTPC26MAR335PE"},{"symbol":"NTPC","strikePrice":40000,"optionType":"PE","expiry":"2016-04-28","ts":"NTPC26APR400PE"},{"symbol":"NTPC","strikePrice":23000,"optionType":"CE","expiry":"2016-04-28","ts":"NTPC26APR230CE"},{"symbol":"NTPC","strikePrice":45750,"optionType":"PE","expiry":"2016-02-25","ts":"NTPC26FEB457.5PE"},{"symbol":"NTPC","strikePrice":43750,"optionType":"PE","expiry":"2016-02-25","ts":"NTPC26FEB437.5PE"},{"symbol":"NTPC","strikePrice":30000,"optionType":"CE","expiry":"2016-03-30","ts":"NTPC26MAR300CE"},{"symbol":"NTPC","strikePrice":35500,"optionType":"CE","expiry":"2016-03-30","ts":"NTPC26MAR355CE"},{"symbol":"NTPC","strikePrice":38750,"optionType":"CE","expiry":"2016-02-25","ts":"NTPC26FEB387.5CE"},{"symbol":"NTPC","strikePrice":46500,"optionType":"PE","expiry":"2016-02-25","ts":"NTPC26FEB465PE"},{"symbol":"NTPC","strikePrice":33500,"optionType":"CE","expiry":"2016-02-25","ts":"NTPC26FEB335CE"},{"symbol":"NTPC","strikePrice":51000,"optionType":"CE","expiry":"2016-04-28","ts":"NTPC26APR510CE"},{"symbol":"NTPC","strikePrice":52000,"optionType":"PE","expiry":"2016-02-25","ts":"NTPC26FEB520PE"},{"symbol":"NTPC","strikePrice":42750,"optionType":"PE","expiry":"2016-03-30","ts":"NTPC26MAR427.5PE"},{"symbol":"NTPC","strikePrice":38000,"optionType":"CE","expiry":"2016-04-28","ts":"NTPC26APR380CE"},{"symbol":"NTPC","strikePrice":27500,"optionType":"CE","expiry":"2016-04-28","ts":"NTPC26APR275CE"},{"symbol":"NTPC","strikePrice":33000,"optionType":"CE","expiry":"2016-02-25","ts":"NTPC26FEB330CE"},{"symbol":"NTPC","strikePrice":45000,"optionType":"PE","expiry":"2016-04-28","ts":"NTPC26APR450PE"},{"symbol":"NTPC","strikePrice":34500,"optionType":"PE","expiry":"2016-04-28","ts":"NTPC26APR345PE"},{"symbol":"NTPC","strikePrice":41500,"optionType":"PE","expiry":"2016-04-28","ts":"NTPC26APR415PE"},{"symbol":"NTPC","strikePrice":38500,"optionType":"PE","expiry":"2016-04-28","ts":"NTPC26APR385PE"},{"symbol":"NTPC","strikePrice":-1,"optionType":"XX","expiry":"2016-03-30","ts":"NTPC26MARFUT"},{"symbol":"NTPC","strikePrice":48500,"optionType":"CE","expiry":"2016-02-25","ts":"NTPC26FEB485CE"},{"symbol":"NTPC","strikePrice":43000,"optionType":"PE","expiry":"2016-04-28","ts":"NTPC26APR430PE"},{"symbol":"NTPC","strikePrice":33000,"optionType":"CE","expiry":"2016-03-30","ts":"NTPC26MAR330CE"},{"symbol":"NTPC","strikePrice":40750,"optionType":"PE","expiry":"2016-03-30","ts":"NTPC26MAR407.5PE"},{"symbol":"NTPC","strikePrice":29500,"optionType":"PE","expiry":"2016-02-25","ts":"NTPC26FEB295PE"},{"symbol":"NTPC","strikePrice":32500,"optionType":"CE","expiry":"2016-04-28","ts":"NTPC26APR325CE"},{"symbol":"NTPC","strikePrice":34250,"optionType":"CE","expiry":"2016-03-30","ts":"NTPC26MAR342.5CE"},{"symbol":"NTPC","strikePrice":45500,"optionType":"CE","expiry":"2016-03-30","ts":"NTPC26MAR455CE"},{"symbol":"NTPC","strikePrice":36250,"optionType":"PE","expiry":"2016-02-25","ts":"NTPC26FEB362.5PE"},{"symbol":"NTPC","strikePrice":48500,"optionType":"PE","expiry":"2016-03-30","ts":"NTPC26MAR485PE"},{"symbol":"NTPC","strikePrice":40250,"optionType":"PE","expiry":"2016-03-30","ts":"NTPC26MAR402.5PE"},{"symbol":"NTPC","strikePrice":25000,"optionType":"CE","expiry":"2016-02-25","ts":"NTPC26FEB250CE"},{"symbol":"NTPC","strikePrice":35250,"optionType":"CE","expiry":"2016-03-30","ts":"NTPC26MAR352.5CE"},{"symbol":"NTPC","strikePrice":50000,"optionType":"CE","expiry":"2016-03-30","ts":"NTPC26MAR500CE"},{"symbol":"NTPC","strikePrice":42750,"optionType":"CE","expiry":"2016-02-25","ts":"NTPC26FEB427.5CE"},{"symbol":"NTPC","strikePrice":46000,"optionType":"PE","expiry":"2016-02-25","ts":"NTPC26FEB460PE"},{"symbol":"NTPC","strikePrice":24500,"optionType":"CE","expiry":"2016-03-30","ts":"NTPC26MAR245CE"},{"symbol":"NTPC","strikePrice":41250,"optionType":"PE","expiry":"2016-03-30","ts":"NTPC26MAR412.5PE"},{"symbol":"NTPC","strikePrice":34000,"optionType":"CE","expiry":"2016-04-28","ts":"NTPC26APR340CE"},{"symbol":"NTPC","strikePrice":26250,"optionType":"CE","expiry":"2016-03-30","ts":"NTPC26MAR262.5CE"},{"symbol":"NTPC","strikePrice":33250,"optionType":"CE","expiry":"2016-03-30","ts":"NTPC26MAR332.5CE"},{"symbol":"NTPC","strikePrice":25500,"optionType":"PE","expiry":"2016-03-30","ts":"NTPC26MAR255PE"},{"symbol":"NTPC","strikePrice":35500,"optionType":"PE","expiry":"2016-04-28","ts":"NTPC26APR355PE"},{"symbol":"NTPC","strikePrice":28250,"optionType":"PE","expiry":"2016-02-25","ts":"NTPC26FEB282.5PE"},{"symbol":"NTPC","strikePrice":30000,"optionType":"CE","expiry":"2016-04-28","ts":"NTPC26APR300CE"},{"symbol":"NTPC","strikePrice":44250,"optionType":"PE","expiry":"2016-02-25","ts":"NTPC26FEB442.5PE"},{"symbol":"NTPC","strikePrice":47000,"optionType":"CE","expiry":"2016-02-25","ts":"NTPC26FEB470CE"},{"symbol":"NTPC","strikePrice":36000,"optionType":"PE","expiry":"2016-03-30","ts":"NTPC26MAR360PE"},{"symbol":"NTPC","strikePrice":39500,"optionType":"CE","expiry":"2016-02-25","ts":"NTPC26FEB395CE"},{"symbol":"NTPC","strikePrice":32500,"optionType":"PE","expiry":"2016-03-30","ts":"NTPC26MAR325PE"},{"symbol":"NTPC","strikePrice":24000,"optionType":"CE","expiry":"2016-04-28","ts":"NTPC26APR240CE"},{"symbol":"NTPC","strikePrice":38500,"optionType":"CE","expiry":"2016-03-30","ts":"NTPC26MAR385CE"},{"symbol":"NTPC","strikePrice":36500,"optionType":"CE","expiry":"2016-03-30","ts":"NTPC26MAR365CE"},{"symbol":"NTPC","strikePrice":27250,"optionType":"CE","expiry":"2016-02-25","ts":"NTPC26FEB272.5CE"},{"symbol":"NTPC","strikePrice":35500,"optionType":"CE","expiry":"2016-02-25","ts":"NTPC26FEB355CE"},{"symbol":"NTPC","strikePrice":49000,"optionType":"CE","expiry":"2016-04-28","ts":"NTPC26APR490CE"},{"symbol":"NTPC","strikePrice":22500,"optionType":"PE","expiry":"2016-03-30","ts":"NTPC26MAR225PE"},{"symbol":"NTPC","strikePrice":28500,"optionType":"PE","expiry":"2016-02-25","ts":"NTPC26FEB285PE"},{"symbol":"NTPC","strikePrice":28500,"optionType":"PE","expiry":"2016-03-30","ts":"NTPC26MAR285PE"},{"symbol":"NTPC","strikePrice":39250,"optionType":"PE","expiry":"2016-02-25","ts":"NTPC26FEB392.5PE"},{"symbol":"NTPC","strikePrice":44750,"optionType":"CE","expiry":"2016-02-25","ts":"NTPC26FEB447.5CE"},{"symbol":"NTPC","strikePrice":37250,"optionType":"CE","expiry":"2016-03-30","ts":"NTPC26MAR372.5CE"},{"symbol":"NTPC","strikePrice":43500,"optionType":"PE","expiry":"2016-03-30","ts":"NTPC26MAR435PE"},{"symbol":"NTPC","strikePrice":20000,"optionType":"CE","expiry":"2016-02-25","ts":"NTPC26FEB200CE"},{"symbol":"NTPC","strikePrice":41250,"optionType":"CE","expiry":"2016-02-25","ts":"NTPC26FEB412.5CE"},{"symbol":"NTPC","strikePrice":41500,"optionType":"CE","expiry":"2016-02-25","ts":"NTPC26FEB415CE"},{"symbol":"NTPC","strikePrice":20500,"optionType":"PE","expiry":"2016-03-30","ts":"NTPC26MAR205PE"},{"symbol":"NTPC","strikePrice":29000,"optionType":"CE","expiry":"2016-04-28","ts":"NTPC26APR290CE"},{"symbol":"NTPC","strikePrice":37000,"optionType":"PE","expiry":"2016-02-25","ts":"NTPC26FEB370PE"},{"symbol":"NTPC","strikePrice":51500,"optionType":"CE","expiry":"2016-02-25","ts":"NTPC26FEB515CE"},{"symbol":"NTPC","strikePrice":42000,"optionType":"CE","expiry":"2016-03-30","ts":"NTPC26MAR420CE"},{"symbol":"NTPC","strikePrice":45750,"optionType":"CE","expiry":"2016-02-25","ts":"NTPC26FEB457.5CE"},{"symbol":"NTPC","strikePrice":30250,"optionType":"CE","expiry":"2016-03-30","ts":"NTPC26MAR302.5CE"},{"symbol":"NTPC","strikePrice":33000,"optionType":"PE","expiry":"2016-04-28","ts":"NTPC26APR330PE"},{"symbol":"NTPC","strikePrice":36500,"optionType":"CE","expiry":"2016-02-25","ts":"NTPC26FEB365CE"},{"symbol":"NTPC","strikePrice":26750,"optionType":"PE","expiry":"2016-03-30","ts":"NTPC26MAR267.5PE"},{"symbol":"NTPC","strikePrice":32250,"optionType":"PE","expiry":"2016-03-30","ts":"NTPC26MAR322.5PE"},{"symbol":"NTPC","strikePrice":36000,"optionType":"CE","expiry":"2016-02-25","ts":"NTPC26FEB360CE"},{"symbol":"NTPC","strikePrice":32250,"optionType":"CE","expiry":"2016-02-25","ts":"NTPC26FEB322.5CE"},{"symbol":"NTPC","strikePrice":33250,"optionType":"CE","expiry":"2016-02-25","ts":"NTPC26FEB332.5CE"},{"symbol":"NTPC","strikePrice":39500,"optionType":"PE","expiry":"2016-04-28","ts":"NTPC26APR395PE"},{"symbol":"NTPC","strikePrice":49500,"optionType":"PE","expiry":"2016-03-30","ts":"NTPC26MAR495PE"},{"symbol":"NTPC","strikePrice":37250,"optionType":"PE","expiry":"2016-03-30","ts":"NTPC26MAR372.5PE"},{"symbol":"NTPC","strikePrice":37750,"optionType":"PE","expiry":"2016-02-25","ts":"NTPC26FEB377.5PE"},{"symbol":"NTPC","strikePrice":43500,"optionType":"PE","expiry":"2016-02-25","ts":"NTPC26FEB435PE"},{"symbol":"NTPC","strikePrice":19000,"optionType":"PE","expiry":"2016-04-28","ts":"NTPC26APR190PE"},{"symbol":"NTPC","strikePrice":50000,"optionType":"CE","expiry":"2016-04-28","ts":"NTPC26APR500CE"},{"symbol":"NTPC","strikePrice":40000,"optionType":"PE","expiry":"2016-03-30","ts":"NTPC26MAR400PE"},{"symbol":"NTPC","strikePrice":33750,"optionType":"PE","expiry":"2016-03-30","ts":"NTPC26MAR337.5PE"},{"symbol":"NTPC","strikePrice":49500,"optionType":"CE","expiry":"2016-03-30","ts":"NTPC26MAR495CE"},{"symbol":"NTPC","strikePrice":29750,"optionType":"PE","expiry":"2016-02-25","ts":"NTPC26FEB297.5PE"},{"symbol":"NTPC","strikePrice":26500,"optionType":"PE","expiry":"2016-02-25","ts":"NTPC26FEB265PE"},{"symbol":"NTPC","strikePrice":37000,"optionType":"CE","expiry":"2016-04-28","ts":"NTPC26APR370CE"},{"symbol":"NTPC","strikePrice":34250,"optionType":"PE","expiry":"2016-02-25","ts":"NTPC26FEB342.5PE"},{"symbol":"NTPC","strikePrice":49000,"optionType":"PE","expiry":"2016-03-30","ts":"NTPC26MAR490PE"},{"symbol":"NTPC","strikePrice":26000,"optionType":"CE","expiry":"2016-02-25","ts":"NTPC26FEB260CE"},{"symbol":"NTPC","strikePrice":44000,"optionType":"PE","expiry":"2016-03-30","ts":"NTPC26MAR440PE"},{"symbol":"NTPC","strikePrice":31000,"optionType":"CE","expiry":"2016-04-28","ts":"NTPC26APR310CE"},{"symbol":"NTPC","strikePrice":25750,"optionType":"PE","expiry":"2016-02-25","ts":"NTPC26FEB257.5PE"},{"symbol":"NTPC","strikePrice":40250,"optionType":"CE","expiry":"2016-03-30","ts":"NTPC26MAR402.5CE"},{"symbol":"NTPC","strikePrice":28500,"optionType":"CE","expiry":"2016-03-30","ts":"NTPC26MAR285CE"},{"symbol":"NTPC","strikePrice":29000,"optionType":"PE","expiry":"2016-04-28","ts":"NTPC26APR290PE"},{"symbol":"NTPC","strikePrice":41000,"optionType":"CE","expiry":"2016-04-28","ts":"NTPC26APR410CE"},{"symbol":"NTPC","strikePrice":32000,"optionType":"PE","expiry":"2016-03-30","ts":"NTPC26MAR320PE"},{"symbol":"NTPC","strikePrice":43000,"optionType":"CE","expiry":"2016-03-30","ts":"NTPC26MAR430CE"},{"symbol":"NTPC","strikePrice":22500,"optionType":"PE","expiry":"2016-02-25","ts":"NTPC26FEB225PE"},{"symbol":"NTPC","strikePrice":27000,"optionType":"PE","expiry":"2016-03-30","ts":"NTPC26MAR270PE"},{"symbol":"NTPC","strikePrice":31750,"optionType":"CE","expiry":"2016-03-30","ts":"NTPC26MAR317.5CE"},{"symbol":"NTPC","strikePrice":20000,"optionType":"PE","expiry":"2016-04-28","ts":"NTPC26APR200PE"},{"symbol":"NTPC","strikePrice":27750,"optionType":"CE","expiry":"2016-02-25","ts":"NTPC26FEB277.5CE"},{"symbol":"NTPC","strikePrice":51500,"optionType":"PE","expiry":"2016-02-25","ts":"NTPC26FEB515PE"},{"symbol":"NTPC","strikePrice":43250,"optionType":"PE","expiry":"2016-02-25","ts":"NTPC26FEB432.5PE"},{"symbol":"NTPC","strikePrice":39000,"optionType":"PE","expiry":"2016-04-28","ts":"NTPC26APR390PE"},{"symbol":"NTPC","strikePrice":41750,"optionType":"PE","expiry":"2016-02-25","ts":"NTPC26FEB417.5PE"},{"symbol":"NTPC","strikePrice":37750,"optionType":"CE","expiry":"2016-02-25","ts":"NTPC26FEB377.5CE"},{"symbol":"NTPC","strikePrice":52000,"optionType":"CE","expiry":"2016-02-25","ts":"NTPC26FEB520CE"},{"symbol":"NTPC","strikePrice":33500,"optionType":"CE","expiry":"2016-04-28","ts":"NTPC26APR335CE"},{"symbol":"NTPC","strikePrice":27250,"optionType":"CE","expiry":"2016-03-30","ts":"NTPC26MAR272.5CE"},{"symbol":"NTPC","strikePrice":26250,"optionType":"PE","expiry":"2016-02-25","ts":"NTPC26FEB262.5PE"},{"symbol":"NTPC","strikePrice":44000,"optionType":"PE","expiry":"2016-04-28","ts":"NTPC26APR440PE"},{"symbol":"NTPC","strikePrice":38500,"optionType":"CE","expiry":"2016-04-28","ts":"NTPC26APR385CE"},{"symbol":"NTPC","strikePrice":41000,"optionType":"PE","expiry":"2016-04-28","ts":"NTPC26APR410PE"},{"symbol":"NTPC","strikePrice":40500,"optionType":"CE","expiry":"2016-02-25","ts":"NTPC26FEB405CE"},{"symbol":"NTPC","strikePrice":44000,"optionType":"CE","expiry":"2016-03-30","ts":"NTPC26MAR440CE"},{"symbol":"NTPC","strikePrice":22500,"optionType":"CE","expiry":"2016-02-25","ts":"NTPC26FEB225CE"},{"symbol":"NTPC","strikePrice":34000,"optionType":"PE","expiry":"2016-04-28","ts":"NTPC26APR340PE"},{"symbol":"NTPC","strikePrice":40500,"optionType":"CE","expiry":"2016-03-30","ts":"NTPC26MAR405CE"},{"symbol":"NTPC","strikePrice":38750,"optionType":"CE","expiry":"2016-03-30","ts":"NTPC26MAR387.5CE"},{"symbol":"NTPC","strikePrice":30000,"optionType":"PE","expiry":"2016-02-25","ts":"NTPC26FEB300PE"},{"symbol":"NTPC","strikePrice":28000,"optionType":"PE","expiry":"2016-02-25","ts":"NTPC26FEB280PE"},{"symbol":"NTPC","strikePrice":22000,"optionType":"CE","expiry":"2016-03-30","ts":"NTPC26MAR220CE"},{"symbol":"NTPC","strikePrice":41250,"optionType":"CE","expiry":"2016-03-30","ts":"NTPC26MAR412.5CE"},{"symbol":"NTPC","strikePrice":29500,"optionType":"PE","expiry":"2016-04-28","ts":"NTPC26APR295PE"},{"symbol":"NTPC","strikePrice":28000,"optionType":"PE","expiry":"2016-04-28","ts":"NTPC26APR280PE"},{"symbol":"NTPC","strikePrice":44250,"optionType":"PE","expiry":"2016-03-30","ts":"NTPC26MAR442.5PE"},{"symbol":"NTPC","strikePrice":41750,"optionType":"CE","expiry":"2016-03-30","ts":"NTPC26MAR417.5CE"},{"symbol":"NTPC","strikePrice":27750,"optionType":"PE","expiry":"2016-03-30","ts":"NTPC26MAR277.5PE"},{"symbol":"NTPC","strikePrice":40000,"optionType":"CE","expiry":"2016-02-25","ts":"NTPC26FEB400CE"},{"symbol":"NTPC","strikePrice":35000,"optionType":"CE","expiry":"2016-02-25","ts":"NTPC26FEB350CE"},{"symbol":"NTPC","strikePrice":24000,"optionType":"CE","expiry":"2016-03-30","ts":"NTPC26MAR240CE"},{"symbol":"NTPC","strikePrice":38500,"optionType":"PE","expiry":"2016-02-25","ts":"NTPC26FEB385PE"},{"symbol":"NTPC","strikePrice":24000,"optionType":"PE","expiry":"2016-04-28","ts":"NTPC26APR240PE"},{"symbol":"NTPC","strikePrice":39750,"optionType":"CE","expiry":"2016-02-25","ts":"NTPC26FEB397.5CE"},{"symbol":"NTPC","strikePrice":29000,"optionType":"CE","expiry":"2016-03-30","ts":"NTPC26MAR290CE"},{"symbol":"NTPC","strikePrice":37000,"optionType":"CE","expiry":"2016-02-25","ts":"NTPC26FEB370CE"},{"symbol":"NTPC","strikePrice":44750,"optionType":"PE","expiry":"2016-02-25","ts":"NTPC26FEB447.5PE"},{"symbol":"NTPC","strikePrice":40000,"optionType":"CE","expiry":"2016-03-30","ts":"NTPC26MAR400CE"},{"symbol":"NTPC","strikePrice":26750,"optionType":"PE","expiry":"2016-02-25","ts":"NTPC26FEB267.5PE"},{"symbol":"NTPC","strikePrice":20500,"optionType":"CE","expiry":"2016-03-30","ts":"NTPC26MAR205CE"},{"symbol":"NTPC","strikePrice":41000,"optionType":"CE","expiry":"2016-02-25","ts":"NTPC26FEB410CE"},{"symbol":"NTPC","strikePrice":36750,"optionType":"PE","expiry":"2016-03-30","ts":"NTPC26MAR367.5PE"},{"symbol":"NTPC","strikePrice":43250,"optionType":"CE","expiry":"2016-03-30","ts":"NTPC26MAR432.5CE"},{"symbol":"NTPC","strikePrice":30750,"optionType":"CE","expiry":"2016-03-30","ts":"NTPC26MAR307.5CE"},{"symbol":"NTPC","strikePrice":52000,"optionType":"CE","expiry":"2016-03-30","ts":"NTPC26MAR520CE"},{"symbol":"NTPC","strikePrice":31750,"optionType":"PE","expiry":"2016-02-25","ts":"NTPC26FEB317.5PE"},{"symbol":"NTPC","strikePrice":22000,"optionType":"PE","expiry":"2016-04-28","ts":"NTPC26APR220PE"},{"symbol":"NTPC","strikePrice":37500,"optionType":"PE","expiry":"2016-04-28","ts":"NTPC26APR375PE"},{"symbol":"NTPC","strikePrice":23000,"optionType":"PE","expiry":"2016-04-28","ts":"NTPC26APR230PE"},{"symbol":"NTPC","strikePrice":29500,"optionType":"CE","expiry":"2016-03-30","ts":"NTPC26MAR295CE"},{"symbol":"NTPC","strikePrice":30750,"optionType":"CE","expiry":"2016-02-25","ts":"NTPC26FEB307.5CE"},{"symbol":"NTPC","strikePrice":38500,"optionType":"CE","expiry":"2016-02-25","ts":"NTPC26FEB385CE"},{"symbol":"NTPC","strikePrice":30500,"optionType":"PE","expiry":"2016-03-30","ts":"NTPC26MAR305PE"},{"symbol":"NTPC","strikePrice":27500,"optionType":"PE","expiry":"2016-04-28","ts":"NTPC26APR275PE"},{"symbol":"NTPC","strikePrice":38000,"optionType":"CE","expiry":"2016-02-25","ts":"NTPC26FEB380CE"},{"symbol":"NTPC","strikePrice":23500,"optionType":"CE","expiry":"2016-02-25","ts":"NTPC26FEB235CE"},{"symbol":"NTPC","strikePrice":39250,"optionType":"CE","expiry":"2016-02-25","ts":"NTPC26FEB392.5CE"},{"symbol":"NTPC","strikePrice":26500,"optionType":"CE","expiry":"2016-03-30","ts":"NTPC26MAR265CE"},{"symbol":"NTPC","strikePrice":26500,"optionType":"PE","expiry":"2016-03-30","ts":"NTPC26MAR265PE"},{"symbol":"NTPC","strikePrice":28750,"optionType":"CE","expiry":"2016-03-30","ts":"NTPC26MAR287.5CE"},{"symbol":"NTPC","strikePrice":41500,"optionType":"CE","expiry":"2016-04-28","ts":"NTPC26APR415CE"},{"symbol":"NTPC","strikePrice":20000,"optionType":"CE","expiry":"2016-04-28","ts":"NTPC26APR200CE"},{"symbol":"NTPC","strikePrice":46500,"optionType":"CE","expiry":"2016-03-30","ts":"NTPC26MAR465CE"},{"symbol":"NTPC","strikePrice":50000,"optionType":"PE","expiry":"2016-02-25","ts":"NTPC26FEB500PE"},{"symbol":"NTPC","strikePrice":50000,"optionType":"PE","expiry":"2016-04-28","ts":"NTPC26APR500PE"},{"symbol":"NTPC","strikePrice":26250,"optionType":"CE","expiry":"2016-02-25","ts":"NTPC26FEB262.5CE"},{"symbol":"NTPC","strikePrice":41500,"optionType":"PE","expiry":"2016-02-25","ts":"NTPC26FEB415PE"},{"symbol":"NTPC","strikePrice":40000,"optionType":"CE","expiry":"2016-04-28","ts":"NTPC26APR400CE"},{"symbol":"NTPC","strikePrice":31750,"optionType":"CE","expiry":"2016-02-25","ts":"NTPC26FEB317.5CE"},{"symbol":"NTPC","strikePrice":34250,"optionType":"CE","expiry":"2016-02-25","ts":"NTPC26FEB342.5CE"},{"symbol":"NTPC","strikePrice":37500,"optionType":"CE","expiry":"2016-02-25","ts":"NTPC26FEB375CE"},{"symbol":"NTPC","strikePrice":46500,"optionType":"PE","expiry":"2016-03-30","ts":"NTPC26MAR465PE"},{"symbol":"NTPC","strikePrice":43750,"optionType":"CE","expiry":"2016-02-25","ts":"NTPC26FEB437.5CE"},{"symbol":"NTPC","strikePrice":21000,"optionType":"CE","expiry":"2016-02-25","ts":"NTPC26FEB210CE"},{"symbol":"NTPC","strikePrice":21000,"optionType":"CE","expiry":"2016-04-28","ts":"NTPC26APR210CE"},{"symbol":"NTPC","strikePrice":44500,"optionType":"PE","expiry":"2016-04-28","ts":"NTPC26APR445PE"},{"symbol":"NTPC","strikePrice":34500,"optionType":"CE","expiry":"2016-02-25","ts":"NTPC26FEB345CE"},{"symbol":"NTPC","strikePrice":25000,"optionType":"PE","expiry":"2016-04-28","ts":"NTPC26APR250PE"},{"symbol":"NTPC","strikePrice":24500,"optionType":"PE","expiry":"2016-03-30","ts":"NTPC26MAR245PE"},{"symbol":"NTPC","strikePrice":39750,"optionType":"PE","expiry":"2016-03-30","ts":"NTPC26MAR397.5PE"},{"symbol":"NTPC","strikePrice":42500,"optionType":"PE","expiry":"2016-03-30","ts":"NTPC26MAR425PE"},{"symbol":"NTPC","strikePrice":42000,"optionType":"PE","expiry":"2016-02-25","ts":"NTPC26FEB420PE"},{"symbol":"NTPC","strikePrice":28500,"optionType":"CE","expiry":"2016-02-25","ts":"NTPC26FEB285CE"},{"symbol":"NTPC","strikePrice":27750,"optionType":"CE","expiry":"2016-03-30","ts":"NTPC26MAR277.5CE"},{"symbol":"NTPC","strikePrice":31000,"optionType":"PE","expiry":"2016-03-30","ts":"NTPC26MAR310PE"},{"symbol":"NTPC","strikePrice":29250,"optionType":"CE","expiry":"2016-03-30","ts":"NTPC26MAR292.5CE"},{"symbol":"NTPC","strikePrice":36500,"optionType":"PE","expiry":"2016-02-25","ts":"NTPC26FEB365PE"},{"symbol":"NTPC","strikePrice":51000,"optionType":"CE","expiry":"2016-03-30","ts":"NTPC26MAR510CE"},{"symbol":"NTPC","strikePrice":34750,"optionType":"CE","expiry":"2016-02-25","ts":"NTPC26FEB347.5CE"},{"symbol":"NTPC","strikePrice":36750,"optionType":"PE","expiry":"2016-02-25","ts":"NTPC26FEB367.5PE"},{"symbol":"NTPC","strikePrice":30500,"optionType":"CE","expiry":"2016-02-25","ts":"NTPC26FEB305CE"},{"symbol":"NTPC","strikePrice":21000,"optionType":"PE","expiry":"2016-03-30","ts":"NTPC26MAR210PE"},{"symbol":"NTPC","strikePrice":29500,"optionType":"PE","expiry":"2016-03-30","ts":"NTPC26MAR295PE"},{"symbol":"NTPC","strikePrice":23000,"optionType":"PE","expiry":"2016-02-25","ts":"NTPC26FEB230PE"},{"symbol":"NTPC","strikePrice":48500,"optionType":"PE","expiry":"2016-02-25","ts":"NTPC26FEB485PE"},{"symbol":"NTPC","strikePrice":25500,"optionType":"CE","expiry":"2016-04-28","ts":"NTPC26APR255CE"},{"symbol":"NTPC","strikePrice":33000,"optionType":"CE","expiry":"2016-04-28","ts":"NTPC26APR330CE"},{"symbol":"NTPC","strikePrice":20000,"optionType":"CE","expiry":"2016-03-30","ts":"NTPC26MAR200CE"},{"symbol":"NTPC","strikePrice":24000,"optionType":"PE","expiry":"2016-02-25","ts":"NTPC26FEB240PE"},{"symbol":"NTPC","strikePrice":37750,"optionType":"CE","expiry":"2016-03-30","ts":"NTPC26MAR377.5CE"},{"symbol":"NTPC","strikePrice":22500,"optionType":"CE","expiry":"2016-03-30","ts":"NTPC26MAR225CE"},{"symbol":"NTPC","strikePrice":37750,"optionType":"PE","expiry":"2016-03-30","ts":"NTPC26MAR377.5PE"},{"symbol":"NTPC","strikePrice":31000,"optionType":"CE","expiry":"2016-03-30","ts":"NTPC26MAR310CE"},{"symbol":"NTPC","strikePrice":23000,"optionType":"CE","expiry":"2016-02-25","ts":"NTPC26FEB230CE"},{"symbol":"NTPC","strikePrice":47000,"optionType":"PE","expiry":"2016-02-25","ts":"NTPC26FEB470PE"},{"symbol":"NTPC","strikePrice":36750,"optionType":"CE","expiry":"2016-02-25","ts":"NTPC26FEB367.5CE"},{"symbol":"NTPC","strikePrice":21000,"optionType":"CE","expiry":"2016-03-30","ts":"NTPC26MAR210CE"},{"symbol":"NTPC","strikePrice":39000,"optionType":"PE","expiry":"2016-02-25","ts":"NTPC26FEB390PE"},{"symbol":"NTPC","strikePrice":27500,"optionType":"CE","expiry":"2016-02-25","ts":"NTPC26FEB275CE"},{"symbol":"NTPC","strikePrice":47000,"optionType":"PE","expiry":"2016-03-30","ts":"NTPC26MAR470PE"},{"symbol":"NTPC","strikePrice":47500,"optionType":"CE","expiry":"2016-03-30","ts":"NTPC26MAR475CE"},{"symbol":"NTPC","strikePrice":34250,"optionType":"PE","expiry":"2016-03-30","ts":"NTPC26MAR342.5PE"},{"symbol":"NTPC","strikePrice":32000,"optionType":"PE","expiry":"2016-02-25","ts":"NTPC26FEB320PE"},{"symbol":"NTPC","strikePrice":43000,"optionType":"PE","expiry":"2016-02-25","ts":"NTPC26FEB430PE"},{"symbol":"NTPC","strikePrice":22000,"optionType":"CE","expiry":"2016-04-28","ts":"NTPC26APR220CE"},{"symbol":"NTPC","strikePrice":25750,"optionType":"PE","expiry":"2016-03-30","ts":"NTPC26MAR257.5PE"},{"symbol":"NTPC","strikePrice":47000,"optionType":"PE","expiry":"2016-04-28","ts":"NTPC26APR470PE"},{"symbol":"NTPC","strikePrice":29750,"optionType":"CE","expiry":"2016-02-25","ts":"NTPC26FEB297.5CE"},{"symbol":"NTPC","strikePrice":45250,"optionType":"CE","expiry":"2016-02-25","ts":"NTPC26FEB452.5CE"},{"symbol":"NTPC","strikePrice":26500,"optionType":"PE","expiry":"2016-04-28","ts":"NTPC26APR265PE"},{"symbol":"NTPC","strikePrice":32000,"optionType":"CE","expiry":"2016-02-25","ts":"NTPC26FEB320CE"},{"symbol":"NTPC","strikePrice":44000,"optionType":"PE","expiry":"2016-02-25","ts":"NTPC26FEB440PE"},{"symbol":"NTPC","strikePrice":40000,"optionType":"PE","expiry":"2016-02-25","ts":"NTPC26FEB400PE"},{"symbol":"NTPC","strikePrice":21500,"optionType":"CE","expiry":"2016-02-25","ts":"NTPC26FEB215CE"},{"symbol":"NTPC","strikePrice":38000,"optionType":"PE","expiry":"2016-04-28","ts":"NTPC26APR380PE"},{"symbol":"NTPC","strikePrice":31250,"optionType":"PE","expiry":"2016-03-30","ts":"NTPC26MAR312.5PE"},{"symbol":"NTPC","strikePrice":39000,"optionType":"CE","expiry":"2016-04-28","ts":"NTPC26APR390CE"},{"symbol":"NTPC","strikePrice":50000,"optionType":"PE","expiry":"2016-03-30","ts":"NTPC26MAR500PE"},{"symbol":"NTPC","strikePrice":38250,"optionType":"CE","expiry":"2016-02-25","ts":"NTPC26FEB382.5CE"},{"symbol":"NTPC","strikePrice":46000,"optionType":"PE","expiry":"2016-03-30","ts":"NTPC26MAR460PE"},{"symbol":"NTPC","strikePrice":28000,"optionType":"CE","expiry":"2016-02-25","ts":"NTPC26FEB280CE"},{"symbol":"NTPC","strikePrice":36000,"optionType":"PE","expiry":"2016-02-25","ts":"NTPC26FEB360PE"},{"symbol":"NTPC","strikePrice":46000,"optionType":"CE","expiry":"2016-03-30","ts":"NTPC26MAR460CE"},{"symbol":"NTPC","strikePrice":39500,"optionType":"PE","expiry":"2016-02-25","ts":"NTPC26FEB395PE"},{"symbol":"NTPC","strikePrice":52000,"optionType":"CE","expiry":"2016-04-28","ts":"NTPC26APR520CE"},{"symbol":"NTPC","strikePrice":19500,"optionType":"CE","expiry":"2016-03-30","ts":"NTPC26MAR195CE"},{"symbol":"NTPC","strikePrice":43000,"optionType":"CE","expiry":"2016-04-28","ts":"NTPC26APR430CE"},{"symbol":"NTPC","strikePrice":26000,"optionType":"PE","expiry":"2016-02-25","ts":"NTPC26FEB260PE"},{"symbol":"NTPC","strikePrice":20500,"optionType":"PE","expiry":"2016-02-25","ts":"NTPC26FEB205PE"},{"symbol":"NTPC","strikePrice":27250,"optionType":"PE","expiry":"2016-03-30","ts":"NTPC26MAR272.5PE"},{"symbol":"NTPC","strikePrice":36250,"optionType":"CE","expiry":"2016-02-25","ts":"NTPC26FEB362.5CE"},{"symbol":"NTPC","strikePrice":37500,"optionType":"PE","expiry":"2016-03-30","ts":"NTPC26MAR375PE"},{"symbol":"NTPC","strikePrice":26000,"optionType":"CE","expiry":"2016-04-28","ts":"NTPC26APR260CE"},{"symbol":"NTPC","strikePrice":36000,"optionType":"CE","expiry":"2016-04-28","ts":"NTPC26APR360CE"},{"symbol":"NTPC","strikePrice":38750,"optionType":"PE","expiry":"2016-03-30","ts":"NTPC26MAR387.5PE"},{"symbol":"NTPC","strikePrice":41500,"optionType":"CE","expiry":"2016-03-30","ts":"NTPC26MAR415CE"},{"symbol":"NTPC","strikePrice":41750,"optionType":"PE","expiry":"2016-03-30","ts":"NTPC26MAR417.5PE"},{"symbol":"NTPC","strikePrice":35750,"optionType":"CE","expiry":"2016-02-25","ts":"NTPC26FEB357.5CE"},{"symbol":"NTPC","strikePrice":52000,"optionType":"PE","expiry":"2016-03-30","ts":"NTPC26MAR520PE"},{"symbol":"NTPC","strikePrice":27500,"optionType":"PE","expiry":"2016-03-30","ts":"NTPC26MAR275PE"},{"symbol":"NTPC","strikePrice":45250,"optionType":"CE","expiry":"2016-03-30","ts":"NTPC26MAR452.5CE"},{"symbol":"NTPC","strikePrice":30250,"optionType":"CE","expiry":"2016-02-25","ts":"NTPC26FEB302.5CE"},{"symbol":"NTPC","strikePrice":51000,"optionType":"CE","expiry":"2016-02-25","ts":"NTPC26FEB510CE"},{"symbol":"NTPC","strikePrice":47500,"optionType":"PE","expiry":"2016-02-25","ts":"NTPC26FEB475PE"},{"symbol":"NTPC","strikePrice":30750,"optionType":"PE","expiry":"2016-02-25","ts":"NTPC26FEB307.5PE"},{"symbol":"NTPC","strikePrice":43250,"optionType":"CE","expiry":"2016-02-25","ts":"NTPC26FEB432.5CE"},{"symbol":"NTPC","strikePrice":43750,"optionType":"CE","expiry":"2016-03-30","ts":"NTPC26MAR437.5CE"},{"symbol":"NTPC","strikePrice":41000,"optionType":"PE","expiry":"2016-02-25","ts":"NTPC26FEB410PE"},{"symbol":"NTPC","strikePrice":30500,"optionType":"PE","expiry":"2016-02-25","ts":"NTPC26FEB305PE"},{"symbol":"NTPC","strikePrice":42500,"optionType":"PE","expiry":"2016-04-28","ts":"NTPC26APR425PE"},{"symbol":"NTPC","strikePrice":42000,"optionType":"PE","expiry":"2016-03-30","ts":"NTPC26MAR420PE"},{"symbol":"NTPC","strikePrice":34750,"optionType":"PE","expiry":"2016-02-25","ts":"NTPC26FEB347.5PE"},{"symbol":"NTPC","strikePrice":36250,"optionType":"CE","expiry":"2016-03-30","ts":"NTPC26MAR362.5CE"},{"symbol":"NTPC","strikePrice":27750,"optionType":"PE","expiry":"2016-02-25","ts":"NTPC26FEB277.5PE"},{"symbol":"NTPC","strikePrice":45750,"optionType":"CE","expiry":"2016-03-30","ts":"NTPC26MAR457.5CE"},{"symbol":"NTPC","strikePrice":37000,"optionType":"CE","expiry":"2016-03-30","ts":"NTPC26MAR370CE"},{"symbol":"NTPC","strikePrice":40750,"optionType":"CE","expiry":"2016-03-30","ts":"NTPC26MAR407.5CE"},{"symbol":"NTPC","strikePrice":43500,"optionType":"CE","expiry":"2016-04-28","ts":"NTPC26APR435CE"},{"symbol":"NTPC","strikePrice":32500,"optionType":"CE","expiry":"2016-03-30","ts":"NTPC26MAR325CE"},{"symbol":"NTPC","strikePrice":29500,"optionType":"CE","expiry":"2016-02-25","ts":"NTPC26FEB295CE"},{"symbol":"NTPC","strikePrice":31500,"optionType":"PE","expiry":"2016-03-30","ts":"NTPC26MAR315PE"},{"symbol":"NTPC","strikePrice":42000,"optionType":"CE","expiry":"2016-02-25","ts":"NTPC26FEB420CE"},{"symbol":"NTPC","strikePrice":31500,"optionType":"PE","expiry":"2016-04-28","ts":"NTPC26APR315PE"},{"symbol":"NTPC","strikePrice":27000,"optionType":"PE","expiry":"2016-02-25","ts":"NTPC26FEB270PE"},{"symbol":"NTPC","strikePrice":40500,"optionType":"PE","expiry":"2016-02-25","ts":"NTPC26FEB405PE"},{"symbol":"NTPC","strikePrice":28000,"optionType":"PE","expiry":"2016-03-30","ts":"NTPC26MAR280PE"},{"symbol":"NTPC","strikePrice":48500,"optionType":"CE","expiry":"2016-03-30","ts":"NTPC26MAR485CE"},{"symbol":"NTPC","strikePrice":39250,"optionType":"PE","expiry":"2016-03-30","ts":"NTPC26MAR392.5PE"},{"symbol":"NTPC","strikePrice":24500,"optionType":"PE","expiry":"2016-02-25","ts":"NTPC26FEB245PE"},{"symbol":"NTPC","strikePrice":49000,"optionType":"CE","expiry":"2016-03-30","ts":"NTPC26MAR490CE"},{"symbol":"NTPC","strikePrice":48000,"optionType":"PE","expiry":"2016-03-30","ts":"NTPC26MAR480PE"},{"symbol":"NTPC","strikePrice":27000,"optionType":"CE","expiry":"2016-02-25","ts":"NTPC26FEB270CE"},{"symbol":"NTPC","strikePrice":39000,"optionType":"PE","expiry":"2016-03-30","ts":"NTPC26MAR390PE"},{"symbol":"NTPC","strikePrice":48000,"optionType":"CE","expiry":"2016-02-25","ts":"NTPC26FEB480CE"},{"symbol":"NTPC","strikePrice":37500,"optionType":"CE","expiry":"2016-03-30","ts":"NTPC26MAR375CE"},{"symbol":"NTPC","strikePrice":45750,"optionType":"PE","expiry":"2016-03-30","ts":"NTPC26MAR457.5PE"},{"symbol":"NTPC","strikePrice":28750,"optionType":"PE","expiry":"2016-02-25","ts":"NTPC26FEB287.5PE"},{"symbol":"NTPC","strikePrice":24500,"optionType":"CE","expiry":"2016-02-25","ts":"NTPC26FEB245CE"},{"symbol":"NTPC","strikePrice":35250,"optionType":"PE","expiry":"2016-03-30","ts":"NTPC26MAR352.5PE"},{"symbol":"NTPC","strikePrice":50500,"optionType":"CE","expiry":"2016-03-30","ts":"NTPC26MAR505CE"},{"symbol":"NTPC","strikePrice":50000,"optionType":"CE","expiry":"2016-02-25","ts":"NTPC26FEB500CE"},{"symbol":"NTPC","strikePrice":26250,"optionType":"PE","expiry":"2016-03-30","ts":"NTPC26MAR262.5PE"},{"symbol":"NTPC","strikePrice":33250,"optionType":"PE","expiry":"2016-03-30","ts":"NTPC26MAR332.5PE"},{"symbol":"NTPC","strikePrice":33750,"optionType":"CE","expiry":"2016-03-30","ts":"NTPC26MAR337.5CE"},{"symbol":"NTPC","strikePrice":36500,"optionType":"CE","expiry":"2016-04-28","ts":"NTPC26APR365CE"},{"symbol":"NTPC","strikePrice":42000,"optionType":"PE","expiry":"2016-04-28","ts":"NTPC26APR420PE"},{"symbol":"NTPC","strikePrice":49000,"optionType":"PE","expiry":"2016-04-28","ts":"NTPC26APR490PE"},{"symbol":"NTPC","strikePrice":21000,"optionType":"PE","expiry":"2016-04-28","ts":"NTPC26APR210PE"},{"symbol":"NTPC","strikePrice":23500,"optionType":"PE","expiry":"2016-02-25","ts":"NTPC26FEB235PE"},{"symbol":"NTPC","strikePrice":48000,"optionType":"CE","expiry":"2016-03-30","ts":"NTPC26MAR480CE"},{"symbol":"NTPC","strikePrice":37500,"optionType":"CE","expiry":"2016-04-28","ts":"NTPC26APR375CE"},{"symbol":"NTPC","strikePrice":38000,"optionType":"PE","expiry":"2016-03-30","ts":"NTPC26MAR380PE"},{"symbol":"NTPC","strikePrice":-1,"optionType":"XX","expiry":"2016-04-28","ts":"NTPC26APRFUT"},{"symbol":"NTPC","strikePrice":31250,"optionType":"PE","expiry":"2016-02-25","ts":"NTPC26FEB312.5PE"},{"symbol":"NTPC","strikePrice":32000,"optionType":"PE","expiry":"2016-04-28","ts":"NTPC26APR320PE"},{"symbol":"NTPC","strikePrice":29250,"optionType":"PE","expiry":"2016-03-30","ts":"NTPC26MAR292.5PE"},{"symbol":"NTPC","strikePrice":19500,"optionType":"CE","expiry":"2016-02-25","ts":"NTPC26FEB195CE"},{"symbol":"NTPC","strikePrice":44500,"optionType":"CE","expiry":"2016-04-28","ts":"NTPC26APR445CE"},{"symbol":"NTPC","strikePrice":21000,"optionType":"PE","expiry":"2016-02-25","ts":"NTPC26FEB210PE"},{"symbol":"NTPC","strikePrice":36250,"optionType":"PE","expiry":"2016-03-30","ts":"NTPC26MAR362.5PE"},{"symbol":"NTPC","strikePrice":43000,"optionType":"CE","expiry":"2016-02-25","ts":"NTPC26FEB430CE"},{"symbol":"NTPC","strikePrice":48000,"optionType":"PE","expiry":"2016-04-28","ts":"NTPC26APR480PE"},{"symbol":"NTPC","strikePrice":35000,"optionType":"CE","expiry":"2016-03-30","ts":"NTPC26MAR350CE"},{"symbol":"NTPC","strikePrice":21500,"optionType":"PE","expiry":"2016-02-25","ts":"NTPC26FEB215PE"},{"symbol":"NTPC","strikePrice":49000,"optionType":"CE","expiry":"2016-02-25","ts":"NTPC26FEB490CE"},{"symbol":"NTPC","strikePrice":33750,"optionType":"CE","expiry":"2016-02-25","ts":"NTPC26FEB337.5CE"},{"symbol":"NTPC","strikePrice":51000,"optionType":"PE","expiry":"2016-03-30","ts":"NTPC26MAR510PE"},{"symbol":"NTPC","strikePrice":26750,"optionType":"CE","expiry":"2016-03-30","ts":"NTPC26MAR267.5CE"},{"symbol":"NTPC","strikePrice":25500,"optionType":"PE","expiry":"2016-04-28","ts":"NTPC26APR255PE"},{"symbol":"NTPC","strikePrice":35500,"optionType":"PE","expiry":"2016-02-25","ts":"NTPC26FEB355PE"},{"symbol":"NTPC","strikePrice":39000,"optionType":"CE","expiry":"2016-02-25","ts":"NTPC26FEB390CE"},{"symbol":"NTPC","strikePrice":27000,"optionType":"PE","expiry":"2016-04-28","ts":"NTPC26APR270PE"},{"symbol":"NTPC","strikePrice":31500,"optionType":"CE","expiry":"2016-03-30","ts":"NTPC26MAR315CE"},{"symbol":"NTPC","strikePrice":25000,"optionType":"CE","expiry":"2016-03-30","ts":"NTPC26MAR250CE"},{"symbol":"NTPC","strikePrice":42750,"optionType":"CE","expiry":"2016-03-30","ts":"NTPC26MAR427.5CE"},{"symbol":"NTPC","strikePrice":45500,"optionType":"PE","expiry":"2016-03-30","ts":"NTPC26MAR455PE"},{"symbol":"NTPC","strikePrice":41000,"optionType":"PE","expiry":"2016-03-30","ts":"NTPC26MAR410PE"},{"symbol":"NTPC","strikePrice":20500,"optionType":"CE","expiry":"2016-02-25","ts":"NTPC26FEB205CE"},{"symbol":"NTPC","strikePrice":32000,"optionType":"CE","expiry":"2016-04-28","ts":"NTPC26APR320CE"},{"symbol":"NTPC","strikePrice":33250,"optionType":"PE","expiry":"2016-02-25","ts":"NTPC26FEB332.5PE"},{"symbol":"NTPC","strikePrice":25750,"optionType":"CE","expiry":"2016-03-30","ts":"NTPC26MAR257.5CE"},{"symbol":"NTPC","strikePrice":33000,"optionType":"PE","expiry":"2016-03-30","ts":"NTPC26MAR330PE"},{"symbol":"NTPC","strikePrice":45500,"optionType":"CE","expiry":"2016-04-28","ts":"NTPC26APR455CE"},{"symbol":"NTPC","strikePrice":38500,"optionType":"PE","expiry":"2016-03-30","ts":"NTPC26MAR385PE"},{"symbol":"NTPC","strikePrice":28000,"optionType":"CE","expiry":"2016-04-28","ts":"NTPC26APR280CE"},{"symbol":"NTPC","strikePrice":36500,"optionType":"PE","expiry":"2016-03-30","ts":"NTPC26MAR365PE"},{"symbol":"NTPC","strikePrice":44000,"optionType":"CE","expiry":"2016-02-25","ts":"NTPC26FEB440CE"},{"symbol":"NTPC","strikePrice":30500,"optionType":"CE","expiry":"2016-04-28","ts":"NTPC26APR305CE"},{"symbol":"NTPC","strikePrice":27250,"optionType":"PE","expiry":"2016-02-25","ts":"NTPC26FEB272.5PE"},{"symbol":"NTPC","strikePrice":36000,"optionType":"PE","expiry":"2016-04-28","ts":"NTPC26APR360PE"},{"symbol":"NTPC","strikePrice":31750,"optionType":"PE","expiry":"2016-03-30","ts":"NTPC26MAR317.5PE"},{"symbol":"NTPC","strikePrice":44500,"optionType":"CE","expiry":"2016-02-25","ts":"NTPC26FEB445CE"},{"symbol":"NTPC","strikePrice":32500,"optionType":"PE","expiry":"2016-04-28","ts":"NTPC26APR325PE"},{"symbol":"NTPC","strikePrice":34750,"optionType":"PE","expiry":"2016-03-30","ts":"NTPC26MAR347.5PE"},{"symbol":"NTPC","strikePrice":33000,"optionType":"PE","expiry":"2016-02-25","ts":"NTPC26FEB330PE"},{"symbol":"NTPC","strikePrice":30500,"optionType":"CE","expiry":"2016-03-30","ts":"NTPC26MAR305CE"},{"symbol":"NTPC","strikePrice":32750,"optionType":"PE","expiry":"2016-02-25","ts":"NTPC26FEB327.5PE"},{"symbol":"NTPC","strikePrice":31000,"optionType":"PE","expiry":"2016-02-25","ts":"NTPC26FEB310PE"},{"symbol":"NTPC","strikePrice":46000,"optionType":"CE","expiry":"2016-02-25","ts":"NTPC26FEB460CE"},{"symbol":"NTPC","strikePrice":35000,"optionType":"PE","expiry":"2016-03-30","ts":"NTPC26MAR350PE"},{"symbol":"NTPC","strikePrice":38000,"optionType":"CE","expiry":"2016-03-30","ts":"NTPC26MAR380CE"},{"symbol":"NTPC","strikePrice":31250,"optionType":"CE","expiry":"2016-02-25","ts":"NTPC26FEB312.5CE"},{"symbol":"NTPC","strikePrice":35000,"optionType":"CE","expiry":"2016-04-28","ts":"NTPC26APR350CE"},{"symbol":"NTPC","strikePrice":27500,"optionType":"CE","expiry":"2016-03-30","ts":"NTPC26MAR275CE"},{"symbol":"NTPC","strikePrice":45000,"optionType":"PE","expiry":"2016-02-25","ts":"NTPC26FEB450PE"},{"symbol":"NTPC","strikePrice":40500,"optionType":"CE","expiry":"2016-04-28","ts":"NTPC26APR405CE"},{"symbol":"NTPC","strikePrice":46000,"optionType":"CE","expiry":"2016-04-28","ts":"NTPC26APR460CE"},{"symbol":"NTPC","strikePrice":37500,"optionType":"PE","expiry":"2016-02-25","ts":"NTPC26FEB375PE"},{"symbol":"NTPC","strikePrice":37250,"optionType":"CE","expiry":"2016-02-25","ts":"NTPC26FEB372.5CE"},{"symbol":"NTPC","strikePrice":29750,"optionType":"CE","expiry":"2016-03-30","ts":"NTPC26MAR297.5CE"},{"symbol":"NTPC","strikePrice":42500,"optionType":"CE","expiry":"2016-04-28","ts":"NTPC26APR425CE"},{"symbol":"NTPC","strikePrice":34000,"optionType":"PE","expiry":"2016-03-30","ts":"NTPC26MAR340PE"},{"symbol":"NTPC","strikePrice":37000,"optionType":"PE","expiry":"2016-03-30","ts":"NTPC26MAR370PE"},{"symbol":"NTPC","strikePrice":20000,"optionType":"PE","expiry":"2016-03-30","ts":"NTPC26MAR200PE"},{"symbol":"NTPC","strikePrice":23500,"optionType":"CE","expiry":"2016-03-30","ts":"NTPC26MAR235CE"},{"symbol":"NTPC","strikePrice":26500,"optionType":"CE","expiry":"2016-02-25","ts":"NTPC26FEB265CE"},{"symbol":"NTPC","strikePrice":27000,"optionType":"CE","expiry":"2016-03-30","ts":"NTPC26MAR270CE"},{"symbol":"NTPC","strikePrice":39000,"optionType":"CE","expiry":"2016-03-30","ts":"NTPC26MAR390CE"},{"symbol":"NTPC","strikePrice":29500,"optionType":"CE","expiry":"2016-04-28","ts":"NTPC26APR295CE"},{"symbol":"NTPC","strikePrice":20000,"optionType":"PE","expiry":"2016-02-25","ts":"NTPC26FEB200PE"},{"symbol":"NTPC","strikePrice":28750,"optionType":"PE","expiry":"2016-03-30","ts":"NTPC26MAR287.5PE"},{"symbol":"NTPC","strikePrice":44500,"optionType":"PE","expiry":"2016-02-25","ts":"NTPC26FEB445PE"},{"symbol":"NTPC","strikePrice":38250,"optionType":"CE","expiry":"2016-03-30","ts":"NTPC26MAR382.5CE"},{"symbol":"NTPC","strikePrice":48000,"optionType":"PE","expiry":"2016-02-25","ts":"NTPC26FEB480PE"},{"symbol":"NTPC","strikePrice":39750,"optionType":"CE","expiry":"2016-03-30","ts":"NTPC26MAR397.5CE"},{"symbol":"NTPC","strikePrice":33750,"optionType":"PE","expiry":"2016-02-25","ts":"NTPC26FEB337.5PE"},{"symbol":"NTPC","strikePrice":35750,"optionType":"PE","expiry":"2016-03-30","ts":"NTPC26MAR357.5PE"},{"symbol":"NTPC","strikePrice":45500,"optionType":"PE","expiry":"2016-04-28","ts":"NTPC26APR455PE"},{"symbol":"NTPC","strikePrice":34750,"optionType":"CE","expiry":"2016-03-30","ts":"NTPC26MAR347.5CE"},{"symbol":"NTPC","strikePrice":36000,"optionType":"CE","expiry":"2016-03-30","ts":"NTPC26MAR360CE"},{"symbol":"NTPC","strikePrice":27500,"optionType":"PE","expiry":"2016-02-25","ts":"NTPC26FEB275PE"},{"symbol":"NTPC","strikePrice":28250,"optionType":"CE","expiry":"2016-03-30","ts":"NTPC26MAR282.5CE"},{"symbol":"NTPC","strikePrice":40750,"optionType":"CE","expiry":"2016-02-25","ts":"NTPC26FEB407.5CE"},{"symbol":"NTPC","strikePrice":44750,"optionType":"CE","expiry":"2016-03-30","ts":"NTPC26MAR447.5CE"},{"symbol":"NTPC","strikePrice":46000,"optionType":"PE","expiry":"2016-04-28","ts":"NTPC26APR460PE"},{"symbol":"NTPC","strikePrice":40250,"optionType":"CE","expiry":"2016-02-25","ts":"NTPC26FEB402.5CE"},{"symbol":"NTPC","strikePrice":52000,"optionType":"PE","expiry":"2016-04-28","ts":"NTPC26APR520PE"},{"symbol":"NTPC","strikePrice":41500,"optionType":"PE","expiry":"2016-03-30","ts":"NTPC26MAR415PE"},{"symbol":"NTPC","strikePrice":30000,"optionType":"CE","expiry":"2016-02-25","ts":"NTPC26FEB300CE"},{"symbol":"NTPC","strikePrice":49500,"optionType":"CE","expiry":"2016-02-25","ts":"NTPC26FEB495CE"},{"symbol":"NTPC","strikePrice":42250,"optionType":"PE","expiry":"2016-03-30","ts":"NTPC26MAR422.5PE"},{"symbol":"NTPC","strikePrice":31500,"optionType":"PE","expiry":"2016-02-25","ts":"NTPC26FEB315PE"},{"symbol":"NTPC","strikePrice":25750,"optionType":"CE","expiry":"2016-02-25","ts":"NTPC26FEB257.5CE"},{"symbol":"NTPC","strikePrice":30250,"optionType":"PE","expiry":"2016-03-30","ts":"NTPC26MAR302.5PE"},{"symbol":"NTPC","strikePrice":24000,"optionType":"PE","expiry":"2016-03-30","ts":"NTPC26MAR240PE"},{"symbol":"NTPC","strikePrice":30000,"optionType":"PE","expiry":"2016-04-28","ts":"NTPC26APR300PE"},{"symbol":"NTPC","strikePrice":35000,"optionType":"PE","expiry":"2016-04-28","ts":"NTPC26APR350PE"},{"symbol":"NTPC","strikePrice":43500,"optionType":"CE","expiry":"2016-02-25","ts":"NTPC26FEB435CE"},{"symbol":"NTPC","strikePrice":33500,"optionType":"PE","expiry":"2016-04-28","ts":"NTPC26APR335PE"},{"symbol":"NTPC","strikePrice":42250,"optionType":"PE","expiry":"2016-02-25","ts":"NTPC26FEB422.5PE"},{"symbol":"NTPC","strikePrice":25500,"optionType":"CE","expiry":"2016-02-25","ts":"NTPC26FEB255CE"},{"symbol":"NTPC","strikePrice":31000,"optionType":"CE","expiry":"2016-02-25","ts":"NTPC26FEB310CE"},{"symbol":"NTPC","strikePrice":34000,"optionType":"PE","expiry":"2016-02-25","ts":"NTPC26FEB340PE"},{"symbol":"NTPC","strikePrice":28500,"optionType":"PE","expiry":"2016-04-28","ts":"NTPC26APR285PE"},{"symbol":"NTPC","strikePrice":35500,"optionType":"PE","expiry":"2016-03-30","ts":"NTPC26MAR355PE"},{"symbol":"NTPC","strikePrice":51000,"optionType":"PE","expiry":"2016-02-25","ts":"NTPC26FEB510PE"},{"symbol":"NTPC","strikePrice":38250,"optionType":"CE","expiry":"2026-04-30","ts":"NTPC26APR382.5CE"},{"symbol":"NTPC","strikePrice":36000,"optionType":"PE","expiry":"2026-04-30","ts":"NTPC26APR360PE"},{"symbol":"NTPC","strikePrice":33250,"optionType":"PE","expiry":"2026-03-25","ts":"NTPC26MAR332.5PE"},{"symbol":"NTPC","strikePrice":36750,"optionType":"CE","expiry":"2026-02-26","ts":"NTPC26FEB367.5CE"},{"symbol":"NTPC","strikePrice":34000,"optionType":"PE","expiry":"2026-04-30","ts":"NTPC26APR340PE"},{"symbol":"NTPC","strikePrice":34500,"optionType":"PE","expiry":"2026-02-26","ts":"NTPC26FEB345PE"},{"symbol":"NTPC","strikePrice":35500,"optionType":"PE","expiry":"2026-04-30","ts":"NTPC26APR355PE"},{"symbol":"NTPC","strikePrice":33000,"optionType":"CE","expiry":"2026-03-25","ts":"NTPC26MAR330CE"},{"symbol":"NTPC","strikePrice":36250,"optionType":"CE","expiry":"2026-02-26","ts":"NTPC26FEB362.5CE"},{"symbol":"NTPC","strikePrice":31000,"optionType":"CE","expiry":"2026-02-26","ts":"NTPC26FEB310CE"},{"symbol":"NTPC","strikePrice":31500,"optionType":"PE","expiry":"2026-02-26","ts":"NTPC26FEB315PE"},{"symbol":"NTPC","strikePrice":33250,"optionType":"CE","expiry":"2026-04-30","ts":"NTPC26APR332.5CE"},{"symbol":"NTPC","strikePrice":33500,"optionType":"CE","expiry":"2026-03-25","ts":"NTPC26MAR335CE"},{"symbol":"NTPC","strikePrice":34500,"optionType":"CE","expiry":"2026-02-26","ts":"NTPC26FEB345CE"},{"symbol":"NTPC","strikePrice":38000,"optionType":"CE","expiry":"2026-04-30","ts":"NTPC26APR380CE"},{"symbol":"NTPC","strikePrice":37500,"optionType":"PE","expiry":"2026-02-26","ts":"NTPC26FEB375PE"},{"symbol":"NTPC","strikePrice":37000,"optionType":"CE","expiry":"2026-03-25","ts":"NTPC26MAR370CE"},{"symbol":"NTPC","strikePrice":32250,"optionType":"CE","expiry":"2026-03-25","ts":"NTPC26MAR322.5CE"},{"symbol":"NTPC","strikePrice":38000,"optionType":"PE","expiry":"2026-03-25","ts":"NTPC26MAR380PE"},{"symbol":"NTPC","strikePrice":30750,"optionType":"CE","expiry":"2026-02-26","ts":"NTPC26FEB307.5CE"},{"symbol":"NTPC","strikePrice":34250,"optionType":"CE","expiry":"2026-03-25","ts":"NTPC26MAR342.5CE"},{"symbol":"NTPC","strikePrice":38000,"optionType":"PE","expiry":"2026-02-26","ts":"NTPC26FEB380PE"},{"symbol":"NTPC","strikePrice":33000,"optionType":"PE","expiry":"2026-04-30","ts":"NTPC26APR330PE"},{"symbol":"NTPC","strikePrice":38500,"optionType":"PE","expiry":"2026-03-25","ts":"NTPC26MAR385PE"},{"symbol":"NTPC","strikePrice":31750,"optionType":"CE","expiry":"2026-03-25","ts":"NTPC26MAR317.5CE"},{"symbol":"NTPC","strikePrice":38750,"optionType":"PE","expiry":"2026-04-30","ts":"NTPC26APR387.5PE"},{"symbol":"NTPC","strikePrice":35000,"optionType":"PE","expiry":"2026-02-26","ts":"NTPC26FEB350PE"},{"symbol":"NTPC","strikePrice":34750,"optionType":"CE","expiry":"2026-02-26","ts":"NTPC26FEB347.5CE"},{"symbol":"NTPC","strikePrice":34750,"optionType":"PE","expiry":"2026-03-25","ts":"NTPC26MAR347.5PE"},{"symbol":"NTPC","strikePrice":30250,"optionType":"CE","expiry":"2026-02-26","ts":"NTPC26FEB302.5CE"},{"symbol":"NTPC","strikePrice":32750,"optionType":"PE","expiry":"2026-04-30","ts":"NTPC26APR327.5PE"},{"symbol":"NTPC","strikePrice":33750,"optionType":"PE","expiry":"2026-04-30","ts":"NTPC26APR337.5PE"},{"symbol":"NTPC","strikePrice":34500,"optionType":"CE","expiry":"2026-03-25","ts":"NTPC26MAR345CE"},{"symbol":"NTPC","strikePrice":38750,"optionType":"PE","expiry":"2026-02-26","ts":"NTPC26FEB387.5PE"},{"symbol":"NTPC","strikePrice":33500,"optionType":"CE","expiry":"2026-02-26","ts":"NTPC26FEB335CE"},{"symbol":"NTPC","strikePrice":35750,"optionType":"PE","expiry":"2026-03-25","ts":"NTPC26MAR357.5PE"},{"symbol":"NTPC","strikePrice":34250,"optionType":"PE","expiry":"2026-02-26","ts":"NTPC26FEB342.5PE"},{"symbol":"NTPC","strikePrice":31000,"optionType":"PE","expiry":"2026-03-25","ts":"NTPC26MAR310PE"},{"symbol":"NTPC","strikePrice":33000,"optionType":"PE","expiry":"2026-02-26","ts":"NTPC26FEB330PE"},{"symbol":"NTPC","strikePrice":37750,"optionType":"CE","expiry":"2026-03-25","ts":"NTPC26MAR377.5CE"},{"symbol":"NTPC","strikePrice":35750,"optionType":"CE","expiry":"2026-02-26","ts":"NTPC26FEB357.5CE"},{"symbol":"NTPC","strikePrice":35250,"optionType":"PE","expiry":"2026-03-25","ts":"NTPC26MAR352.5PE"},{"symbol":"NTPC","strikePrice":33500,"optionType":"CE","expiry":"2026-04-30","ts":"NTPC26APR335CE"},{"symbol":"NTPC","strikePrice":30750,"optionType":"PE","expiry":"2026-02-26","ts":"NTPC26FEB307.5PE"},{"symbol":"NTPC","strikePrice":36500,"optionType":"CE","expiry":"2026-03-25","ts":"NTPC26MAR365CE"},{"symbol":"NTPC","strikePrice":32500,"optionType":"CE","expiry":"2026-02-26","ts":"NTPC26FEB325CE"},{"symbol":"NTPC","strikePrice":34000,"optionType":"PE","expiry":"2026-02-26","ts":"NTPC26FEB340PE"},{"symbol":"NTPC","strikePrice":38750,"optionType":"PE","expiry":"2026-03-25","ts":"NTPC26MAR387.5PE"},{"symbol":"NTPC","strikePrice":36750,"optionType":"CE","expiry":"2026-03-25","ts":"NTPC26MAR367.5CE"},{"symbol":"NTPC","strikePrice":36000,"optionType":"CE","expiry":"2026-02-26","ts":"NTPC26FEB360CE"},{"symbol":"NTPC","strikePrice":33500,"optionType":"PE","expiry":"2026-03-25","ts":"NTPC26MAR335PE"},{"symbol":"NTPC","strikePrice":37000,"optionType":"PE","expiry":"2026-03-25","ts":"NTPC26MAR370PE"},{"symbol":"NTPC","strikePrice":31500,"optionType":"PE","expiry":"2026-03-25","ts":"NTPC26MAR315PE"},{"symbol":"NTPC","strikePrice":38500,"optionType":"CE","expiry":"2026-03-25","ts":"NTPC26MAR385CE"},{"symbol":"NTPC","strikePrice":37250,"optionType":"PE","expiry":"2026-04-30","ts":"NTPC26APR372.5PE"},{"symbol":"NTPC","strikePrice":36500,"optionType":"CE","expiry":"2026-04-30","ts":"NTPC26APR365CE"},{"symbol":"NTPC","strikePrice":37250,"optionType":"PE","expiry":"2026-03-25","ts":"NTPC26MAR372.5PE"},{"symbol":"NTPC","strikePrice":37000,"optionType":"PE","expiry":"2026-04-30","ts":"NTPC26APR370PE"},{"symbol":"NTPC","strikePrice":35250,"optionType":"PE","expiry":"2026-02-26","ts":"NTPC26FEB352.5PE"},{"symbol":"NTPC","strikePrice":36000,"optionType":"PE","expiry":"2026-02-26","ts":"NTPC26FEB360PE"},{"symbol":"NTPC","strikePrice":33250,"optionType":"CE","expiry":"2026-03-25","ts":"NTPC26MAR332.5CE"},{"symbol":"NTPC","strikePrice":32000,"optionType":"PE","expiry":"2026-03-25","ts":"NTPC26MAR320PE"},{"symbol":"NTPC","strikePrice":32500,"optionType":"CE","expiry":"2026-03-25","ts":"NTPC26MAR325CE"},{"symbol":"NTPC","strikePrice":36500,"optionType":"PE","expiry":"2026-04-30","ts":"NTPC26APR365PE"},{"symbol":"NTPC","strikePrice":35750,"optionType":"PE","expiry":"2026-04-30","ts":"NTPC26APR357.5PE"},{"symbol":"NTPC","strikePrice":35250,"optionType":"PE","expiry":"2026-04-30","ts":"NTPC26APR352.5PE"},{"symbol":"NTPC","strikePrice":30750,"optionType":"CE","expiry":"2026-03-25","ts":"NTPC26MAR307.5CE"},{"symbol":"NTPC","strikePrice":36750,"optionType":"PE","expiry":"2026-03-25","ts":"NTPC26MAR367.5PE"},{"symbol":"NTPC","strikePrice":33250,"optionType":"PE","expiry":"2026-04-30","ts":"NTPC26APR332.5PE"},{"symbol":"NTPC","strikePrice":33500,"optionType":"PE","expiry":"2026-04-30","ts":"NTPC26APR335PE"},{"symbol":"NTPC","strikePrice":37500,"optionType":"CE","expiry":"2026-02-26","ts":"NTPC26FEB375CE"},{"symbol":"NTPC","strikePrice":32000,"optionType":"CE","expiry":"2026-02-26","ts":"NTPC26FEB320CE"},{"symbol":"NTPC","strikePrice":38250,"optionType":"CE","expiry":"2026-02-26","ts":"NTPC26FEB382.5CE"},{"symbol":"NTPC","strikePrice":38250,"optionType":"PE","expiry":"2026-04-30","ts":"NTPC26APR382.5PE"},{"symbol":"NTPC","strikePrice":33750,"optionType":"CE","expiry":"2026-03-25","ts":"NTPC26MAR337.5CE"},{"symbol":"NTPC","strikePrice":35750,"optionType":"CE","expiry":"2026-04-30","ts":"NTPC26APR357.5CE"},{"symbol":"NTPC","strikePrice":32250,"optionType":"CE","expiry":"2026-02-26","ts":"NTPC26FEB322.5CE"},{"symbol":"NTPC","strikePrice":37000,"optionType":"CE","expiry":"2026-04-30","ts":"NTPC26APR370CE"},{"symbol":"NTPC","strikePrice":32250,"optionType":"PE","expiry":"2026-02-26","ts":"NTPC26FEB322.5PE"},{"symbol":"NTPC","strikePrice":38250,"optionType":"PE","expiry":"2026-02-26","ts":"NTPC26FEB382.5PE"},{"symbol":"NTPC","strikePrice":35500,"optionType":"CE","expiry":"2026-03-25","ts":"NTPC26MAR355CE"},{"symbol":"NTPC","strikePrice":36250,"optionType":"CE","expiry":"2026-03-25","ts":"NTPC26MAR362.5CE"},{"symbol":"NTPC","strikePrice":37000,"optionType":"PE","expiry":"2026-02-26","ts":"NTPC26FEB370PE"},{"symbol":"NTPC","strikePrice":37250,"optionType":"CE","expiry":"2026-04-30","ts":"NTPC26APR372.5CE"},{"symbol":"NTPC","strikePrice":34750,"optionType":"CE","expiry":"2026-04-30","ts":"NTPC26APR347.5CE"},{"symbol":"NTPC","strikePrice":34750,"optionType":"PE","expiry":"2026-02-26","ts":"NTPC26FEB347.5PE"},{"symbol":"NTPC","strikePrice":30000,"optionType":"PE","expiry":"2026-02-26","ts":"NTPC26FEB300PE"},{"symbol":"NTPC","strikePrice":32000,"optionType":"CE","expiry":"2026-03-25","ts":"NTPC26MAR320CE"},{"symbol":"NTPC","strikePrice":37750,"optionType":"CE","expiry":"2026-02-26","ts":"NTPC26FEB377.5CE"},{"symbol":"NTPC","strikePrice":34000,"optionType":"PE","expiry":"2026-03-25","ts":"NTPC26MAR340PE"},{"symbol":"NTPC","strikePrice":38750,"optionType":"CE","expiry":"2026-03-25","ts":"NTPC26MAR387.5CE"},{"symbol":"NTPC","strikePrice":36750,"optionType":"CE","expiry":"2026-04-30","ts":"NTPC26APR367.5CE"},{"symbol":"NTPC","strikePrice":33750,"optionType":"PE","expiry":"2026-02-26","ts":"NTPC26FEB337.5PE"},{"symbol":"NTPC","strikePrice":31750,"optionType":"PE","expiry":"2026-03-25","ts":"NTPC26MAR317.5PE"},{"symbol":"NTPC","strikePrice":37750,"optionType":"PE","expiry":"2026-04-30","ts":"NTPC26APR377.5PE"},{"symbol":"NTPC","strikePrice":34250,"optionType":"CE","expiry":"2026-04-30","ts":"NTPC26APR342.5CE"},{"symbol":"NTPC","strikePrice":32500,"optionType":"PE","expiry":"2026-02-26","ts":"NTPC26FEB325PE"},{"symbol":"NTPC","strikePrice":35750,"optionType":"CE","expiry":"2026-03-25","ts":"NTPC26MAR357.5CE"},{"symbol":"NTPC","strikePrice":34500,"optionType":"CE","expiry":"2026-04-30","ts":"NTPC26APR345CE"},{"symbol":"NTPC","strikePrice":31000,"optionType":"CE","expiry":"2026-03-25","ts":"NTPC26MAR310CE"},{"symbol":"NTPC","strikePrice":37500,"optionType":"PE","expiry":"2026-03-25","ts":"NTPC26MAR375PE"},{"symbol":"NTPC","strikePrice":36250,"optionType":"CE","expiry":"2026-04-30","ts":"NTPC26APR362.5CE"},{"symbol":"NTPC","strikePrice":30250,"optionType":"PE","expiry":"2026-02-26","ts":"NTPC26FEB302.5PE"},{"symbol":"NTPC","strikePrice":33000,"optionType":"CE","expiry":"2026-04-30","ts":"NTPC26APR330CE"},{"symbol":"NTPC","strikePrice":33750,"optionType":"CE","expiry":"2026-04-30","ts":"NTPC26APR337.5CE"},{"symbol":"NTPC","strikePrice":35000,"optionType":"PE","expiry":"2026-03-25","ts":"NTPC26MAR350PE"},{"symbol":"NTPC","strikePrice":38250,"optionType":"CE","expiry":"2026-03-25","ts":"NTPC26MAR382.5CE"},{"symbol":"NTPC","strikePrice":32750,"optionType":"CE","expiry":"2026-03-25","ts":"NTPC26MAR327.5CE"},{"symbol":"NTPC","strikePrice":33250,"optionType":"CE","expiry":"2026-02-26","ts":"NTPC26FEB332.5CE"},{"symbol":"NTPC","strikePrice":32250,"optionType":"PE","expiry":"2026-03-25","ts":"NTPC26MAR322.5PE"},{"symbol":"NTPC","strikePrice":34250,"optionType":"CE","expiry":"2026-02-26","ts":"NTPC26FEB342.5CE"},{"symbol":"NTPC","strikePrice":35750,"optionType":"PE","expiry":"2026-02-26","ts":"NTPC26FEB357.5PE"},{"symbol":"NTPC","strikePrice":37750,"optionType":"PE","expiry":"2026-02-26","ts":"NTPC26FEB377.5PE"},{"symbol":"NTPC","strikePrice":30000,"optionType":"CE","expiry":"2026-02-26","ts":"NTPC26FEB300CE"},{"symbol":"NTPC","strikePrice":37500,"optionType":"CE","expiry":"2026-03-25","ts":"NTPC26MAR375CE"},{"symbol":"NTPC","strikePrice":32000,"optionType":"PE","expiry":"2026-02-26","ts":"NTPC26FEB320PE"},{"symbol":"NTPC","strikePrice":31250,"optionType":"PE","expiry":"2026-03-25","ts":"NTPC26MAR312.5PE"},{"symbol":"NTPC","strikePrice":34250,"optionType":"PE","expiry":"2026-03-25","ts":"NTPC26MAR342.5PE"},{"symbol":"NTPC","strikePrice":38000,"optionType":"CE","expiry":"2026-03-25","ts":"NTPC26MAR380CE"},{"symbol":"NTPC","strikePrice":33750,"optionType":"CE","expiry":"2026-02-26","ts":"NTPC26FEB337.5CE"},{"symbol":"NTPC","strikePrice":33500,"optionType":"PE","expiry":"2026-02-26","ts":"NTPC26FEB335PE"},{"symbol":"NTPC","strikePrice":36500,"optionType":"PE","expiry":"2026-02-26","ts":"NTPC26FEB365PE"},{"symbol":"NTPC","strikePrice":34000,"optionType":"CE","expiry":"2026-04-30","ts":"NTPC26APR340CE"},{"symbol":"NTPC","strikePrice":35000,"optionType":"CE","expiry":"2026-04-30","ts":"NTPC26APR350CE"},{"symbol":"NTPC","strikePrice":34000,"optionType":"CE","expiry":"2026-03-25","ts":"NTPC26MAR340CE"},{"symbol":"NTPC","strikePrice":34250,"optionType":"PE","expiry":"2026-04-30","ts":"NTPC26APR342.5PE"},{"symbol":"NTPC","strikePrice":35000,"optionType":"CE","expiry":"2026-03-25","ts":"NTPC26MAR350CE"},{"symbol":"NTPC","strikePrice":37000,"optionType":"CE","expiry":"2026-02-26","ts":"NTPC26FEB370CE"},{"symbol":"NTPC","strikePrice":38750,"optionType":"CE","expiry":"2026-04-30","ts":"NTPC26APR387.5CE"},{"symbol":"NTPC","strikePrice":31250,"optionType":"PE","expiry":"2026-02-26","ts":"NTPC26FEB312.5PE"},{"symbol":"NTPC","strikePrice":37750,"optionType":"PE","expiry":"2026-03-25","ts":"NTPC26MAR377.5PE"},{"symbol":"NTPC","strikePrice":36250,"optionType":"PE","expiry":"2026-03-25","ts":"NTPC26MAR362.5PE"},{"symbol":"NTPC","strikePrice":36000,"optionType":"CE","expiry":"2026-04-30","ts":"NTPC26APR360CE"},{"symbol":"NTPC","strikePrice":38500,"optionType":"PE","expiry":"2026-02-26","ts":"NTPC26FEB385PE"},{"symbol":"NTPC","strikePrice":30500,"optionType":"CE","expiry":"2026-02-26","ts":"NTPC26FEB305CE"},{"symbol":"NTPC","strikePrice":33750,"optionType":"PE","expiry":"2026-03-25","ts":"NTPC26MAR337.5PE"},{"symbol":"NTPC","strikePrice":36000,"optionType":"CE","expiry":"2026-03-25","ts":"NTPC26MAR360CE"},{"symbol":"NTPC","strikePrice":37250,"optionType":"CE","expiry":"2026-03-25","ts":"NTPC26MAR372.5CE"},{"symbol":"NTPC","strikePrice":36500,"optionType":"CE","expiry":"2026-02-26","ts":"NTPC26FEB365CE"},{"symbol":"NTPC","strikePrice":31000,"optionType":"PE","expiry":"2026-02-26","ts":"NTPC26FEB310PE"},{"symbol":"NTPC","strikePrice":35500,"optionType":"PE","expiry":"2026-02-26","ts":"NTPC26FEB355PE"},{"symbol":"NTPC","strikePrice":30500,"optionType":"PE","expiry":"2026-02-26","ts":"NTPC26FEB305PE"},{"symbol":"NTPC","strikePrice":34500,"optionType":"PE","expiry":"2026-04-30","ts":"NTPC26APR345PE"},{"symbol":"NTPC","strikePrice":36250,"optionType":"PE","expiry":"2026-02-26","ts":"NTPC26FEB362.5PE"},{"symbol":"NTPC","strikePrice":38500,"optionType":"CE","expiry":"2026-04-30","ts":"NTPC26APR385CE"},{"symbol":"NTPC","strikePrice":33000,"optionType":"PE","expiry":"2026-03-25","ts":"NTPC26MAR330PE"},{"symbol":"NTPC","strikePrice":35500,"optionType":"CE","expiry":"2026-02-26","ts":"NTPC26FEB355CE"},{"symbol":"NTPC","strikePrice":37250,"optionType":"CE","expiry":"2026-02-26","ts":"NTPC26FEB372.5CE"},{"symbol":"NTPC","strikePrice":34000,"optionType":"CE","expiry":"2026-02-26","ts":"NTPC26FEB340CE"},{"symbol":"NTPC","strikePrice":35000,"optionType":"CE","expiry":"2026-02-26","ts":"NTPC26FEB350CE"},{"symbol":"NTPC","strikePrice":37250,"optionType":"PE","expiry":"2026-02-26","ts":"NTPC26FEB372.5PE"},{"symbol":"NTPC","strikePrice":0,"optionType":"XX","expiry":"2026-04-30","ts":"NTPC26APRFUT"},{"symbol":"NTPC","strikePrice":38500,"optionType":"PE","expiry":"2026-04-30","ts":"NTPC26APR385PE"},{"symbol":"NTPC","strikePrice":31500,"optionType":"CE","expiry":"2026-02-26","ts":"NTPC26FEB315CE"},{"symbol":"NTPC","strikePrice":36500,"optionType":"PE","expiry":"2026-03-25","ts":"NTPC26MAR365PE"},{"symbol":"NTPC","strikePrice":38250,"optionType":"PE","expiry":"2026-03-25","ts":"NTPC26MAR382.5PE"},{"symbol":"NTPC","strikePrice":34750,"optionType":"CE","expiry":"2026-03-25","ts":"NTPC26MAR347.5CE"},{"symbol":"NTPC","strikePrice":36750,"optionType":"PE","expiry":"2026-02-26","ts":"NTPC26FEB367.5PE"},{"symbol":"NTPC","strikePrice":31250,"optionType":"CE","expiry":"2026-03-25","ts":"NTPC26MAR312.5CE"},{"symbol":"NTPC","strikePrice":35500,"optionType":"CE","expiry":"2026-04-30","ts":"NTPC26APR355CE"},{"symbol":"NTPC","strikePrice":38000,"optionType":"PE","expiry":"2026-04-30","ts":"NTPC26APR380PE"},{"symbol":"NTPC","strikePrice":35250,"optionType":"CE","expiry":"2026-02-26","ts":"NTPC26FEB352.5CE"},{"symbol":"NTPC","strikePrice":37750,"optionType":"CE","expiry":"2026-04-30","ts":"NTPC26APR377.5CE"},{"symbol":"NTPC","strikePrice":38500,"optionType":"CE","expiry":"2026-02-26","ts":"NTPC26FEB385CE"},{"symbol":"NTPC","strikePrice":37500,"optionType":"PE","expiry":"2026-04-30","ts":"NTPC26APR375PE"},{"symbol":"NTPC","strikePrice":35250,"optionType":"CE","expiry":"2026-04-30","ts":"NTPC26APR352.5CE"},{"symbol":"NTPC","strikePrice":0,"optionType":"XX","expiry":"2026-02-26","ts":"NTPC26FEBFUT"},{"symbol":"NTPC","strikePrice":38750,"optionType":"CE","expiry":"2026-02-26","ts":"NTPC26FEB387.5CE"},{"symbol":"NTPC","strikePrice":36750,"optionType":"PE","expiry":"2026-04-30","ts":"NTPC26APR367.5PE"},{"symbol":"NTPC","strikePrice":0,"optionType":"XX","expiry":"2026-03-25","ts":"NTPC26MARFUT"},{"symbol":"NTPC","strikePrice":36000,"optionType":"PE","expiry":"2026-03-25","ts":"NTPC26MAR360PE"},{"symbol":"NTPC","strikePrice":38000,"optionType":"CE","expiry":"2026-02-26","ts":"NTPC26FEB380CE"},{"symbol":"NTPC","strikePrice":30750,"optionType":"PE","expiry":"2026-03-25","ts":"NTPC26MAR307.5PE"},{"symbol":"NTPC","strikePrice":33000,"optionType":"CE","expiry":"2026-02-26","ts":"NTPC26FEB330CE"},{"symbol":"NTPC","strikePrice":35500,"optionType":"PE","expiry":"2026-03-25","ts":"NTPC26MAR355PE"},{"symbol":"NTPC","strikePrice":32500,"optionType":"PE","expiry":"2026-03-25","ts":"NTPC26MAR325PE"},{"symbol":"NTPC","strikePrice":36250,"optionType":"PE","expiry":"2026-04-30","ts":"NTPC26APR362.5PE"},{"symbol":"NTPC","strikePrice":35250,"optionType":"CE","expiry":"2026-03-25","ts":"NTPC26MAR352.5CE"},{"symbol":"NTPC","strikePrice":34750,"optionType":"PE","expiry":"2026-04-30","ts":"NTPC26APR347.5PE"},{"symbol":"NTPC","strikePrice":30500,"optionType":"CE","expiry":"2026-03-25","ts":"NTPC26MAR305CE"},{"symbol":"NTPC","strikePrice":35000,"optionType":"PE","expiry":"2026-04-30","ts":"NTPC26APR350PE"},{"symbol":"NTPC","strikePrice":31750,"optionType":"PE","expiry":"2026-02-26","ts":"NTPC26FEB317.5PE"},{"symbol":"NTPC","strikePrice":32750,"optionType":"CE","expiry":"2026-02-26","ts":"NTPC26FEB327.5CE"},{"symbol":"NTPC","strikePrice":37500,"optionType":"CE","expiry":"2026-04-30","ts":"NTPC26APR375CE"},{"symbol":"NTPC","strikePrice":31500,"optionType":"CE","expiry":"2026-03-25","ts":"NTPC26MAR315CE"},{"symbol":"NTPC","strikePrice":31750,"optionType":"CE","expiry":"2026-02-26","ts":"NTPC26FEB317.5CE"},{"symbol":"NTPC","strikePrice":32750,"optionType":"PE","expiry":"2026-02-26","ts":"NTPC26FEB327.5PE"},{"symbol":"NTPC","strikePrice":30500,"optionType":"PE","expiry":"2026-03-25","ts":"NTPC26MAR305PE"},{"symbol":"NTPC","strikePrice":34500,"optionType":"PE","expiry":"2026-03-25","ts":"NTPC26MAR345PE"},{"symbol":"NTPC","strikePrice":33250,"optionType":"PE","expiry":"2026-02-26","ts":"NTPC26FEB332.5PE"},{"symbol":"NTPC","strikePrice":32750,"optionType":"PE","expiry":"2026-03-25","ts":"NTPC26MAR327.5PE"},{"symbol":"NTPC","strikePrice":31250,"optionType":"CE","expiry":"2026-02-26","ts":"NTPC26FEB312.5CE"},{"symbol":"NTPC","strikePrice":32750,"optionType":"CE","expiry":"2026-04-30","ts":"NTPC26APR327.5CE"}]